Workbook
Name OLE_LINK1: 'Datos ICP (2)'!#REF!

Sheet Comentario
A2: El IPC de abril registró una variación mensual de 1,2%, llevando la inflación anual a 4,0%, por encima de las expectativas del mercado. El alza estuvo impulsada principalmente por los combustibles y su traspaso al componente de transporte. El componente volátil de energía acumuló un avance mensual de 12,9%, reflejando especialmente los incrementos en los precios de la gasolina y el diésel asociados al shock energético observado a fines de marzo. La inflación subyacente continuó mostrando una dinámica relativamente contenida, con un aumento de 0,5% mensual y 3,5% anual. Tanto los servicios como los bienes subyacentes mantuvieron variaciones acotadas, sin señales relevantes de efectos de segunda vuelta asociados a una aceleración de la demanda. Si bien el traspaso del shock en combustibles sigue siendo limitado fuera de los componentes más volátiles, su impacto continuará siendo monitoreado en los próximos meses. Por su parte, el Banco Central mantuvo la tasa de política monetaria en 4,5%, manteniendo una postura cautelosa ante la incertidumbre asociada a la evolución del conflicto en Medio Oriente, la trayectoria del precio del petróleo y sus potenciales efectos sobre la convergencia inflacionaria.

Sheet Datos ICP (2)
A1: CLICP Index | F1: Cuota Liquidez | AD1: ICP | AE1: Ene | AF1: Feb | AG1: Mar | AH1: Abr | AI1: May | AJ1: Jun | AK1: Jul | AL1: Ago | AM1: Sep | AN1: Oct | AO1: Nov | AP1: Dic | AQ1: Total Año
A2: Fecha | B2: ICP | D2: ICP Norm. | J2: Fondo Liquidez Corriente | K2: 8730-0 | M2: Competencia Relevante (*) | P2: Ene | Q2: Feb | R2: Mar | S2: Abr | T2: May | U2: Jun | V2: Jul | W2: Ago | X2: Sep | Y2: Oct | Z2: Nov | AA2: Dic | AD2: 2006 | AE2: =P3/N3-1 | AF2: =Q3/P3-1 | AG2: =R3/Q3-1 | AH2: =S3/R3-1 | AI2: =T3/S3-1 | AJ2: =U3/T3-1 | AK2: =V3/U3-1 | AL2: =W3/V3-1 | AM2: =X3/W3-1 | ... AP2: =AA3/Z3-1 | AQ2: =AA3/N3-1
A3: 38717 | B3: 10953.14 | K3: SERIE E | N3: =B3 | O3: 2006 | P3: 10996.85 | Q3: 11035.11 | R3: 11078.66 | S3: 11118.82 | T3: 11169.1 | U3: 11215.04 | V3: 11263.22 | W3: 11313.29 | X3: 11360.92 | Y3: 11413.02 | Z3: 11463.01 | AA3: 11512.49 | AD3: 2007 | AE3: =P4/AA3-1 | AF3: =Q4/P4-1 | AG3: =R4/Q4-1 | AH3: =S4/R4-1 | AI3: =T4/S4-1 | AJ3: =U4/T4-1 | AK3: =V4/U4-1 | AL3: =W4/V4-1 | AM3: =X4/W4-1 | ... AP3: =AA4/Z4-1 | AQ3: =AA4/AA3-1
A4: 38748 | B4: 10996.85 | C4: =(B4/B3-1)/(A4-A3)*30 | K4: BCI EFICIENTE | O4: 2007 | P4: 11567.23 | Q4: 11612.68 | R4: 11661.5 | S4: 11712.58 | T4: 11763.78 | U4: 11812.23 | V4: 11866.53 | W4: 11922.48 | X4: 11975.61 | Y4: 12038.9 | Z4: 12096.85 | AA4: 12152.6 | AD4: 2008 | AE4: =P5/AA4-1 | AF4: =Q5/P5-1 | AG4: =R5/Q5-1 | AH4: =S5/R5-1 | AI4: =T5/S5-1 | AJ4: =U5/T5-1 | AK4: =V5/U5-1 | AL4: =W5/V5-1 | AM4: =X5/W5-1 | ... AP4: =AA5/Z5-1 | AQ4: =AA5/AA4-1
A5: 38776 | B5: 11035.11 | C5: =(B5/B4-1)/(A5-A4)*30 | O5: 2008 | P5: 12223.14 | Q5: 12284.88 | R5: 12351.45 | S5: 12416.18 | T5: 12481.48 | U5: 12552.23 | V5: 12628.9 | W5: 12704.63 | X5: 12796.95 | Y5: 12885.37 | Z5: 12970.93 | AA5: 13066.33 | AD5: 2009 | AE5: =P6/AA5-1 | AF5: =Q6/P6-1 | AG5: =R6/Q6-1 | AH5: =S6/R6-1 | AI5: =T6/S6-1 | AJ5: =U6/T6-1 | AK5: =V6/U6-1 | AL5: =W6/V6-1 | AM5: =X6/W6-1 | ... AP5: =AA6/Z6-1 | AQ5: =AA6/AA5-1
A6: 38807 | B6: 11078.66 | C6: =(B6/B5-1)/(A6-A5)*30 | O6: 2009 | P6: 13151.16 | Q6: 13212.09 | R6: 13251.18 | S6: 13272.62 | T6: 13286.96 | U6: 13299.08 | V6: 13305.34 | W6: 13310.07 | X6: 13315.05 | Y6: 13319.74 | Z6: 13324.51 | AA6: 13329.5 | AD6: 2010 | AE6: =P7/AA6-1 | AF6: =Q7/P7-1 | AG6: =R7/Q7-1 | AH6: =S7/R7-1 | AI6: =T7/S7-1 | AJ6: =U7/T7-1 | AK6: =V7/U7-1 | AL6: =W7/V7-1 | AM6: =X7/W7-1 | ... AP6: =AA7/Z7-1 | AQ6: =AA7/AA6-1
A7: 38835 | B7: 11118.82 | C7: =(B7/B6-1)/(A7-A6)*30 | O7: 2010 | P7: 13334.25 | Q7: 13338.53 | R7: 13343.79 | S7: 13348.63 | T7: 13353.5 | U7: 13360.9 | V7: 13373.99 | W7: 13395.21 | X7: 13419.79 | Y7: 13448.69 | Z7: 13483.02 | AA7: 13522.93 | AD7: 2011 | AE7: =P8/AA7-1 | AF7: =Q8/P8-1 | AG7: =R8/Q8-1 | AH7: =S8/R8-1 | AI7: =T8/S8-1 | AJ7: =U8/T8-1 | AK7: =V8/U8-1 | AL7: =W8/V8-1 | AM7: =X8/W8-1 | ... AP7: =AA8/Z8-1 | AQ7: =AA8/AA7-1
A8: 38868 | B8: 11169.1 | C8: =(B8/B7-1)/(A8-A7)*30 | O8: 2011 | P8: 13557.12 | Q8: 13592.3 | R8: 13635.91 | S8: 13682.94 | T8: 13741.06 | U8: 13799.74 | V8: 13858.14 | W8: 13925.03 | X8: 13985.97 | Y8: 14043.21 | Z8: 14110.87 | AA8: 14172.63 | AD8: 2012 | AE8: =P9/AA8-1 | AF8: =Q9/P9-1 | AG8: =R9/Q9-1 | AH8: =S9/R9-1 | AI8: =T9/S9-1 | AJ8: =U9/T9-1 | AK8: =V9/U9-1 | AL8: =W9/V9-1 | AM8: =X9/W9-1 | ... AP8: =AA9/Z9-1 | AQ8: =AA9/AA8-1
A9: 38898 | B9: 11215.04 | C9: =(B9/B8-1)/(A9-A8)*30 | O9: 2012 | P9: 14236.38 | Q9: 14293.67 | R9: 14353.34 | S9: 14415.21 | T9: 14477.55 | U9: 14536.13 | V9: 14600.61 | W9: 14663.33 | X9: 14720.68 | Y9: 14788.56 | Z9: 14850.38 | AA9: 14908.2 | AD9: 2013 | AE9: =P10/AA9-1 | AF9: =Q10/P10-1 | AG9: =R10/Q10-1 | AH9: =S10/R10-1 | AI9: =T10/S10-1 | AJ9: =U10/T10-1 | AK9: =V10/U10-1 | AL9: =W10/V10-1 | AM9: =X10/W10-1 | ... AP9: =AA10/Z10-1 | AQ9: =AA10/AA9-1
A10: 38929 | B10: 11263.22 | C10: =(B10/B9-1)/(A10-A9)*30 | O10: 2013 | P10: 14978.58 | Q10: 15036.94 | R10: 15095.51 | S10: 15164.77 | T10: 15230.38 | U10: 15289.74 | V10: 15360.27 | W10: 15424.43 | X10: 15490.99 | Y10: 15554.36 | Z10: 15615.06 | AA10: 15675.68 | AD10: 2014 | AE10: =P11/AA10-1 | AF10: =Q11/P11-1 | AG10: =R11/Q11-1 | AH10: =S11/R11-1 | AI10: =T11/S11-1 | AJ10: =U11/T11-1 | AK10: =V11/U11-1 | AL10: =W11/V11-1 | AM10: =X11/W11-1 | ... AP10: =AA11/Z11-1 | AQ10: =AA11/AA10-1
A11: 38960 | B11: 11313.29 | C11: =(B11/B10-1)/(A11-A10)*30 | O11: 2014 | P11: 15738.45 | Q11: 15792.47 | R11: 15848.53 | S11: 15901.43 | T11: 15954.5 | U11: 16009.53 | V11: 16063.18 | W11: 16110.55 | X11: 16158.37 | Y11: 16200.86 | Z11: 16240.11 | AA11: 16283.49 | AD11: 2015 | AE11: =P12/AA11-1 | AF11: =Q12/P12-1 | AG11: =R12/Q12-1 | AH11: =S12/R12-1 | AI11: =T12/S12-1 | AJ11: =U12/T12-1 | AK11: =V12/U12-1 | AL11: =W12/V12-1 | AM11: =X12/W12-1 | ... AP11: =AA12/Z12-1 | AQ11: =AA12/AA11-1
A12: 38989 | B12: 11360.92 | C12: =(B12/B11-1)/(A12-A11)*30 | O12: 2015 | P12: 16325.65 | Q12: 16363.77 | R12: 16407.49 | S12: 16448.59 | T12: 16488.37 | U12: 16532.38 | V12: 16575.11 | W12: 16617.94 | X12: 16659.58 | Y12: 16702.94 | Z12: 16749.75 | AA12: 16796.52 | AD12: 2016 | AE12: =P13/AA12-1 | AF12: =Q13/P13-1 | AG12: =R13/Q13-1 | AH12: =S13/R13-1 | AI12: =T13/S13-1 | AJ12: =U13/T13-1 | AK12: =V13/U13-1 | AL12: =W13/V13-1 | AM12: =X13/W13-1 | ... AP12: =AA13/Z13-1 | AQ12: =AA13/AA12-1
A13: 39021 | B13: 11413.02 | C13: =(B13/B12-1)/(A13-A12)*30 | O13: 2016 | P13: 16845.59 | Q13: 16896.43 | R13: 16947.43 | S13: 16995.27 | T13: 17048.23 | U13: 17098.02 | V13: 17149.62 | W13: 17201.38 | X13: 17251.69 | Y13: =+B135 | Z13: =+B136 | AA13: =+B137 | AD13: 2017 | AE13: =P14/AA13-1 | AF13: =+Q14/P14-1 | AG13: =+R14/Q14-1 | AH13: =+S14/R14-1 | AI13: =+T14/S14-1 | AJ13: =+U14/T14-1 | AK13: =+V14/U14-1 | AL13: =+W14/V14-1 | AM13: =+X14/W14-1 | ... AP13: =+AA14/Z14-1 | AQ13: =AA14/AA13-1
A14: 39051 | B14: 11463.01 | C14: =(B14/B13-1)/(A14-A13)*30 | O14: 2017 | P14: =+B138 | Q14: =+B139 | R14: =+B140 | S14: =+B141 | T14: =+B142 | U14: =+$B143 | V14: =+$B144 | W14: =+$B145 | X14: =+$B146 | Y14: =+$B147 | Z14: =+$B148 | AA14: =+$B149 | AD14: 2018 | AE14: =P15/AA14-1 | AF14: =+Q15/P15-1 | AG14: =+R15/Q15-1 | AH14: =+S15/R15-1 | AI14: =+T15/S15-1 | AJ14: =+U15/T15-1 | AK14: =+V15/U15-1 | AL14: =+W15/V15-1 | AM14: =+X15/W15-1 | ... AP14: =+AA15/Z15-1 | AQ14: =+AA15/AA14-1
A15: 39080 | B15: 11512.49 | C15: =(B15/B14-1)/(A15-A14)*30 | O15: 2018 | P15: =+B150 | Q15: =+B151 | R15: =+B152 | S15: =+B153 | T15: =+B154 | U15: =+B155 | V15: =+B156 | W15: =+B157 | X15: =+B158 | Y15: =+B159 | Z15: =+B160 | AA15: =+B161 | AD15: 2019 | AR15: (*)
A16: 39113 | B16: 11567.23 | C16: =(B16/B15-1)/(A16-A15)*30 | O16: 2019 | P16: =+B162 | Q16: =+B163 | R16: =+B164 | S16: =+B165 | T16: =+B166 | U16: =+B167 | V16: =+B168 | W16: =+B169 | X16: =+B170 | Y16: =+B171 | Z16: =+B172 | AA16: =+B173 | AD16: 2020
A17: 39141 | B17: 11612.68 | C17: =(B17/B16-1)/(A17-A16)*30 | O17: 2020 | P17: =+B174 | Q17: =+B175 | R17: =+B176 | S17: =+B177 | T17: =+B178 | U17: =+B179 | V17: =+B180 | W17: =+B181 | X17: =+B182 | Y17: =+B183 | Z17: =+B184 | AA17: =+B185 | AD17: 2021
A18: 39171 | B18: 11661.5 | C18: =(B18/B17-1)/(A18-A17)*30 | O18: 2021 | Q18: =+B187 | R18: =+B188 | S18: =+B189 | T18: =+B190 | U18: =+B191 | V18: =+B192 | W18: =+B193 | X18: =+B194 | Y18: =+B195 | Z18: =+B196 | AA18: =+B197 | AD18: 2022 | AX18: -1 | AY18: -3 | AZ18: -6 | BA18: -12
A19: 39202 | B19: 11712.58 | C19: =(B19/B18-1)/(A19-A18)*30 | O19: 2022 | P19: =+B198 | Q19: =+B199 | R19: =+B200 | S19: =+B201 | T19: =+B202 | U19: =+B203 | V19: =+B204 | W19: =+B205 | X19: =+B206 | Y19: =+B207 | Z19: =+B208 | AA19: =+B209 | AD19: 2023 | AV19: Ingresar mes actual==> | AW19: 46203 | AX19: =EOMONTH($AW19,AX18)+6 | AY19: =EOMONTH($AW19,AY18) | AZ19: =EOMONTH($AW19,AZ18) | BA19: =EOMONTH($AW19,BA18) | BB19: 43100
A20: 39233 | B20: 11763.78 | C20: =(B20/B19-1)/(A20-A19)*30 | O20: 2023 | P20: =+B210 | Q20: =+B211 | R20: =+B212 | S20: =+B213 | T20: =+B214 | U20: =+B215 | V20: =+B216 | W20: =+B217 | X20: =+B218 | Y20: =+B219 | Z20: =+B220 | AA20: =+B221 | AD20: 2024 | AV20: ICP | AW20: =LOOKUP(AW19,$A$3:$A$2973,$B$3:$B$2973) | AX20: =LOOKUP(AX19,$A$3:$A$2973,$B$3:$B$2973) | AY20: =LOOKUP(AY19,$A$3:$A$2973,$B$3:$B$2973) | AZ20: =LOOKUP(AZ19,$A$3:$A$2973,$B$3:$B$2973) | BA20: =LOOKUP(BA19,$A$3:$A$2973,$B$3:$B$2973) | BB20: =LOOKUP(BB19,$A$3:$A$2973,$B$3:$B$2973)
A21: 39262 | B21: 11812.23 | C21: =(B21/B20-1)/(A21-A20)*30 | O21: 2024 | P21: =+B222 | Q21: =+B223 | R21: =+B224 | S21: =+B225 | T21: =+B226 | U21: =+B227 | V21: =+B228 | W21: =+B229 | X21: =+B230 | Y21: =+B231 | Z21: =+B232 | AA21: =+B233 | AD21: 2025 | AF21: =+Q22/P22-1 | AG21: =+R22/Q22-1 | AH21: =+S22/R22-1 | AI21: =+T22/S22-1 | AJ21: =+U22/T22-1 | AK21: =+V22/U22-1 | AL21: =+W22/V22-1 | AM21: =+X22/W22-1 | ... AP21: =+AA22/Z22-1 | AQ21: =+(AA22/P22-1)/COUNTA(AE21:AP21)*12 | AV21: Competencia | AW21: =LOOKUP(AW19,$F$2:$F$2974,$K$2:$K$2974) | AX21: =LOOKUP(AX19,$F$2:$F$2974,$K$2:$K$2974) | AY21: =LOOKUP(AY19,$F$2:$F$2974,$K$2:$K$2974) | AZ21: =LOOKUP(AZ19,$F$2:$F$2974,$K$2:$K$2974) | BA21: =LOOKUP(BA19,$F$2:$F$2974,$K$2:$K$2974) | BB21: =LOOKUP(BB19,$F$2:$F$2974,$K$2:$K$2974)
A22: 39294 | B22: 11866.53 | C22: =(B22/B21-1)/(A22-A21)*30 | O22: 2025 | P22: =+B234 | Q22: =+B235 | R22: =+B236 | S22: =+B237 | T22: =+B238 | U22: =+B239 | V22: =+B240 | W22: =+B241 | X22: =+B242 | Y22: =+B243 | Z22: =+B244 | AA22: =+B245 | AD22: 2026 | AE22: =+P23/AA22-1 | AF22: =+Q23/P23-1 | AG22: =+R23/Q23-1 | AH22: =+S23/R23-1 | AI22: =+T23/S23-1 | AJ22: =+U23/T23-1 | AQ22: =+(U23/P23-1)/COUNTA(AE22:AJ22)*12 | AV22: FIP Liquidez Corriente | AW22: =LOOKUP(AW19,$F$2:$F$2972,$H$2:$H$2972) | AX22: =LOOKUP(AX19,$F$2:$F$2972,$H$2:$H$2972) | AY22: =LOOKUP(AY19,$F$2:$F$2972,$H$2:$H$2972) | AZ22: =LOOKUP(AZ19,$F$2:$F$2972,$H$2:$H$2972) | BA22: =LOOKUP(BA19,$F$2:$F$2972,$H$2:$H$2972) | BB22: =LOOKUP(BB19,$F$2:$F$2972,$H$2:$H$2972)
O23: 2026 | P23: =+B246 | Q23: =+B247 | R23: =+B248 | S23: =+B249 | T23: =+B250 | U23: =+B251
A24: 39325 | B24: 11922.48 | C24: =(B24/B22-1)/(A24-A22)*30 | P24: 31 | Q24: 28 | R24: 31 | S24: 30 | T24: 31 | U24: 30 | V24: 31 | W24: 31 | X24: 30 | Y24: 31 | Z24: 30 | AA24: 31 | AD24: (*) Acum a Mar
A25: 39353 | B25: 11975.61 | C25: =(B25/B24-1)/(A25-A24)*30 | P25: 1 | Q25: 2 | R25: 3 | S25: 4 | T25: 5 | U25: 6 | V25: 7 | W25: 8 | X25: 9 | Y25: 10 | Z25: 11 | AA25: 12
A26: 39386 | B26: 12038.9 | C26: =(B26/B25-1)/(A26-A25)*30 | O26: FONDO LIQUIDEZ CORRIENTE | P26: Ene | Q26: Feb | R26: Mar | S26: Abr | T26: May | U26: Jun | V26: Jul | W26: Ago | X26: Sep | Y26: Oct | Z26: Nov | AA26: Dic
A27: 39416 | B27: 12096.85 | C27: =(B27/B26-1)/(A27-A26)*30 | O27: 2016 | T27: ='[1]Cuota Liquidez '!B2 | U27: =LOOKUP(DATE($O27,U$25,U$24),$A$2:$A$2943,$H$2:$H$2943) | V27: =LOOKUP(DATE($O27,V$25,V$24),$A$2:$A$2943,$H$2:$H$2943) | W27: =LOOKUP(DATE($O27,W$25,W$24),$A$2:$A$2943,$H$2:$H$2943) | X27: =LOOKUP(DATE($O27,X$25,X$24),$A$2:$A$2943,$H$2:$H$2943) | Y27: =LOOKUP(DATE($O27,Y$25,Y$24),$A$2:$A$2943,$H$2:$H$2943) | Z27: =LOOKUP(DATE($O27,Z$25,Z$24),$A$2:$A$2943,$H$2:$H$2943) | AA27: =LOOKUP(DATE($O27,AA$25,AA$24),$A$2:$A$2943,$H$2:$H$2943) | AD27: Presente | AE27: Ene | AF27: Feb | AG27: Mar | AH27: Abr | AI27: May | AJ27: Jun | AK27: Jul | AL27: Ago | AM27: Sep | AN27: Oct | AO27: Nov | AP27: Dic | AQ27: Total Año
A28: 39447 | B28: 12152.6 | C28: =(B28/B27-1)/(A28-A27)*30 | O28: 2017 | P28: =LOOKUP(DATE($O28,P$25,P$24),$A$2:$A$2943,$H$2:$H$2943) | Q28: =LOOKUP(DATE($O28,Q$25,Q$24),$A$2:$A$2943,$H$2:$H$2943) | R28: =LOOKUP(DATE($O28,R$25,R$24),$A$2:$A$2943,$H$2:$H$2943) | S28: =LOOKUP(DATE($O28,S$25,S$24),$A$2:$A$2943,$H$2:$H$2943) | T28: =LOOKUP(DATE($O28,T$25,T$24),$A$2:$A$2943,$H$2:$H$2943) | U28: =LOOKUP(DATE($O28,U$25,U$24),$A$2:$A$2943,$H$2:$H$2943) | V28: =LOOKUP(DATE($O28,V$25,V$24),$A$2:$A$2943,$H$2:$H$2943) | W28: =LOOKUP(DATE($O28,W$25,W$24),$A$2:$A$2943,$H$2:$H$2943) | ... AA28: =LOOKUP(DATE($O28,AA$25,AA$24),$A$2:$A$2943,$H$2:$H$2943) | AD28: 2016 | AW28: Rentabilidad | AX28: Mensual | AY28: Trimestral | AZ28: Semestral | BA28: Anual | BB28: Acum. 2026
A29: 39478 | B29: 12223.14 | C29: =(B29/B28-1)/(A29-A28)*30 | O29: 2018 | P29: =LOOKUP(DATE($O29,P$25,P$24),$A$2:$A$2943,$H$2:$H$2943) | Q29: =LOOKUP(DATE($O29,Q$25,Q$24),$A$2:$A$2943,$H$2:$H$2943) | R29: =LOOKUP(DATE($O29,R$25,R$24),$A$2:$A$2943,$H$2:$H$2943) | S29: =LOOKUP(DATE($O29,S$25,S$24),$A$2:$A$2943,$H$2:$H$2943) | T29: =LOOKUP(DATE($O29,T$25,T$24),$A$2:$A$2943,$H$2:$H$2943) | U29: =LOOKUP(DATE($O29,U$25,U$24),$A$2:$A$2943,$H$2:$H$2943) | V29: =LOOKUP(DATE($O29,V$25,V$24),$A$2:$A$2943,$H$2:$H$2943) | W29: =LOOKUP(DATE($O29,W$25,W$24),$A$2:$A$2943,$H$2:$H$2943) | ... AA29: =LOOKUP(DATE($O29,AA$25,AA$24),$A$2:$A$2943,$H$2:$H$2943) | AD29: 2017 | AR29: (*) | AW29: ICP (Bechmark) | AX29: =$AW20/AX20-1 | AY29: =$AW20/AY20-1 | AZ29: =$AW20/AZ20-1 | BA29: =$AW20/BA20-1 | BB29: =+AQ86
A30: 39507 | B30: 12284.88 | C30: =(B30/B29-1)/(A30-A29)*30 | O30: 2019 | P30: =LOOKUP(DATE($O30,P$25,P$24),$A$2:$A$2943,$H$2:$H$2943) | Q30: =LOOKUP(DATE($O30,Q$25,Q$24),$A$2:$A$2943,$H$2:$H$2943) | R30: =LOOKUP(DATE($O30,R$25,R$24),$A$2:$A$2943,$H$2:$H$2943) | S30: =LOOKUP(DATE($O30,S$25,S$24),$A$2:$A$2943,$H$2:$H$2943) | T30: =LOOKUP(DATE($O30,T$25,T$24),$A$2:$A$2943,$H$2:$H$2943) | U30: =LOOKUP(DATE($O30,U$25,U$24),$A$2:$A$2943,$H$2:$H$2943) | V30: =LOOKUP(DATE($O30,V$25,V$24),$A$2:$A$2943,$H$2:$H$2943) | W30: =LOOKUP(DATE($O30,W$25,W$24),$A$2:$A$2943,$H$2:$H$2943) | ... AA30: =LOOKUP(DATE($O30,AA$25,AA$24),$A$2:$A$2943,$H$2:$H$2943) | AD30: 2018 | AW30: Competencia | AX30: =$AW21/AX21-1 | AY30: =$AW21/AY21-1 | AZ30: =$AW21/AZ21-1 | BA30: =$AW21/BA21-1 | BB30: =+AQ87
A31: 39538 | B31: 12351.45 | C31: =(B31/B30-1)/(A31-A30)*30 | O31: 2020 | P31: =LOOKUP(DATE($O31,P$25,P$24),$A$2:$A$2943,$H$2:$H$2943) | Q31: =LOOKUP(DATE($O31,Q$25,Q$24)+1,$A$2:$A$2943,$H$2:$H$2943) | R31: =LOOKUP(DATE($O31,R$25,R$24)+1,$A$2:$A$2943,$H$2:$H$2943) | S31: =LOOKUP(DATE($O31,S$25,S$24)+1,$A$2:$A$2943,$H$2:$H$2943) | T31: =LOOKUP(DATE($O31,T$25,T$24)+1,$A$2:$A$2943,$H$2:$H$2943) | U31: =LOOKUP(DATE($O31,U$25,U$24)+1,$A$2:$A$2943,$H$2:$H$2943) | V31: =LOOKUP(DATE($O31,V$25,V$24)+1,$A$2:$A$2943,$H$2:$H$2943) | W31: =LOOKUP(DATE($O31,W$25,W$24)+1,$A$2:$A$2943,$H$2:$H$2943) | X31: =LOOKUP(DATE($O31,X$25,X$24)+1,$A$2:$A$2943,$H$2:$H$2943) | Y31: =+G183 | Z31: =+G184 | AA31: =+G185 | AD31: 2019 | AW31: FIP LIQUIDEZ Presente | AX31: =$AW22/AX22-1 | AY31: =$AW22/AY22-1 | AZ31: =$AW22/AZ22-1 | BA31: =$AW22/BA22-1 | BB31: =+AQ88
A32: 39568 | B32: 12416.18 | C32: =(B32/B31-1)/(A32-A31)*30 | O32: 2021 | T32: =+G190 | U32: =+G191 | V32: =+G192 | W32: =+G193 | X32: =+G194 | Y32: =+G195 | Z32: =+G196 | AA32: =+G197+S156 | AD32: 2020
A33: 39598 | B33: 12481.48 | C33: =(B33/B32-1)/(A33-A32)*30 | O33: 2022 | T33: =+G202+S156 | U33: =+G203+S156 | V33: =+G204+S156 | W33: =+G205+S156 | X33: =+G206+S156 | Y33: =+G207+S156 | Z33: =+G208+S156 | AA33: =+G209+S156 | AD33: 2021
A34: 39629 | B34: 12552.23 | C34: =(B34/B33-1)/(A34-A33)*30 | O34: 2023 | W34: =+G217 | X34: =+G218 | Y34: =+G219 | Z34: =+G220 | AA34: =+G221 | AD34: 2022
A35: 39660 | B35: 12628.9 | C35: =(B35/B34-1)/(A35-A34)*30 | O35: 2024 | P35: =+G222 | Q35: =+G223 | R35: =+G224 | S35: =+G225 | T35: =+G226 | U35: =+G227 | V35: =+G228 | W35: =+G229 | X35: =+G230 | Y35: =+G231 | Z35: =+G232 | AA35: =+G233 | AD35: 2023
A36: 39689 | B36: 12704.63 | C36: =(B36/B35-1)/(A36-A35)*30 | O36: 2025 | P36: =+G234 | Q36: =+G235 | R36: =+G236 | S36: =+G237 | T36: =+G238 | U36: =+G239 | V36: =+G240 | W36: =+G241 | X36: =+G242 | Y36: =+G243 | Z36: =+G244 | AA36: =+G245 | AD36: 2024
O37: 2026 | P37: =+G246 | Q37: =+G247 | R37: =+G248 | S37: =+G249 | T37: =+G250 | U37: =+G251 | AD37: 2025 | AF37: =+(Q36/P36-1) | AG37: =+(R36/Q36-1) | AH37: =+(S36/R36-1) | AI37: =+(T36/S36-1) | AJ37: =+(U36/T36-1) | AK37: =+(V36/U36-1) | AL37: =+(W36/V36-1) | AM37: =+(X36/W36-1) | ... AP37: =+(AA36/Z36-1) | AQ37: =+(Z36/P36-1)/COUNTA(AE37:AP37)*12
A38: 39721 | B38: 12796.95 | C38: =(B38/B36-1)/(A38-A36)*30 | P38: 31 | Q38: 28 | R38: 31 | S38: 30 | T38: 31 | U38: 30 | V38: 31 | W38: 31 | X38: 30 | Y38: 31 | Z38: 30 | AA38: 31 | AD38: 2026 | AE38: =+(P37/AA36-1) | AF38: =+(Q37/P37-1) | AG38: =+(R37/Q37-1) | AH38: =+(S37/R37-1) | AI38: =+T37/S37-1 | AJ38: =+U37/T37-1 | AQ38: =+(U37/P37-1)/COUNTA(AE38:AJ38)*12 | AR38: (*)
A39: 39752 | B39: 12885.37 | C39: =(B39/B38-1)/(A39-A38)*30 | P39: 1 | Q39: 2 | R39: 3 | S39: 4 | T39: 5 | U39: 6 | V39: 7 | W39: 8 | X39: 9 | Y39: 10 | Z39: 11 | AA39: 12 | AD39: (*) Acum a Mar
A40: 39780 | B40: 12970.93 | C40: =(B40/B39-1)/(A40-A39)*30 | O40: Competencia | P40: Ene | Q40: Feb | R40: Mar | S40: Abr | T40: May | U40: Jun | V40: Jul | W40: Ago | X40: Sep | Y40: Oct | Z40: Nov | AA40: Dic | AD40: Competencia | AE40: Ene | AF40: Feb | AG40: Mar | AH40: Abr | AI40: May | AJ40: Jun | AK40: Jul | AL40: Ago | AM40: Sep | AN40: Oct | AO40: Nov | AP40: Dic | AQ40: Total Año
A41: 39813 | B41: 13066.33 | C41: =(B41/B40-1)/(A41-A40)*30 | O41: 2016 | P41: =+K126 | Q41: =+K127 | R41: =+K128 | S41: =+K129 | T41: =+K130 | U41: =+K131 | V41: =+K132 | W41: =+K133 | X41: =+K134 | Y41: =+K135 | Z41: =+K136 | AA41: =+K137 | AD41: 2016 | AF41: =+Q41/P41-1 | AG41: =+R41/Q41-1 | AH41: =+S41/R41-1 | AI41: =+T41/S41-1 | AJ41: =+U41/T41-1 | AK41: =+V41/U41-1 | AL41: =+W41/V41-1 | AM41: =+X41/W41-1 | ... AP41: =+AA41/Z41-1 | AQ41: =+AA41/P41-1
A42: 39843 | B42: 13151.16 | C42: =(B42/B41-1)/(A42-A41)*30 | O42: 2017 | P42: =+K138 | Q42: =+K139 | R42: =+K140 | S42: =+K141 | T42: =+K142 | U42: =+$K143 | V42: =+$K144 | W42: =+$K145 | X42: =+$K146 | Y42: =+$K147 | Z42: =+$K148 | AA42: =+K149 | AD42: 2017 | AE42: =+P42/AA41-1 | AF42: =+Q42/P42-1 | AG42: =+R42/Q42-1 | AH42: =+S42/R42-1 | AI42: =+T42/S42-1 | AJ42: =+U42/T42-1 | AK42: =+V42/U42-1 | AL42: =+W42/V42-1 | AM42: =+X42/W42-1 | ... AP42: =+AA42/Z42-1 | AQ42: =+AA35/Y35-1
A43: 39871 | B43: 13212.09 | C43: =(B43/B42-1)/(A43-A42)*30 | O43: 2018 | P43: =+K150 | Q43: =+K151 | R43: =+K152 | S43: =+K153 | T43: =+K154 | U43: =+K155 | V43: =+K156 | W43: =+K157 | X43: =+K158 | Y43: =+K159 | Z43: =+K160 | AA43: =+K161 | AD43: 2018
A44: 39903 | B44: 13251.18 | C44: =(B44/B43-1)/(A44-A43)*30 | O44: 2019 | P44: =+K162 | Q44: =+K163 | R44: =+K164 | S44: =+K165 | T44: =+K166 | U44: =+K167 | V44: =+K168 | W44: =+K169 | X44: =+K170 | Y44: =+K171 | Z44: =+K172 | AA44: =+K173 | AD44: 2019
A45: 39933 | B45: 13272.62 | C45: =(B45/B44-1)/(A45-A44)*30 | O45: 2020 | P45: =+K174 | Q45: =+K175 | R45: =+K176 | S45: =+K177 | T45: =+K178 | U45: =+K179 | V45: =+K180 | W45: =+K181 | X45: =+K182 | Y45: =+K183 | Z45: =+K184 | AA45: =+K185 | AD45: 2020
A46: 39962 | B46: 13286.96 | C46: =(B46/B45-1)/(A46-A45)*30 | O46: 2021 | Q46: =+K187 | R46: =+K188 | S46: =+K189 | T46: =+K190 | U46: =+K191 | V46: =+K192 | W46: =+K193 | X46: =+K194 | Y46: =+K195 | Z46: =+K196 | AA46: =+K197 | AD46: 2021
A47: 39994 | B47: 13299.08 | C47: =(B47/B46-1)/(A47-A46)*30 | O47: 2022 | P47: =+K198 | Q47: =+K199 | R47: =+K200 | S47: =+K201 | T47: =+K202 | U47: =+K203 | V47: =+K204 | W47: =+K205 | X47: =+K206 | Y47: =+K207 | Z47: =+K208 | AA47: =+K209 | AD47: 2022
A48: 40025 | B48: 13305.34 | C48: =(B48/B47-1)/(A48-A47)*30 | O48: 2023 | P48: =+K210 | Q48: =+K211 | R48: =+K212 | S48: =+K213 | T48: =+K214 | U48: =+K215 | V48: =+K216 | W48: =+K217 | X48: =+K218 | Y48: =+K219 | Z48: =+K220 | AA48: =+K221 | AD48: 2023
A49: 40056 | B49: 13310.07 | C49: =(B49/B48-1)/(A49-A48)*30 | O49: 2024 | P49: =+K222 | Q49: =+K223 | R49: =+K224 | S49: =+K225 | T49: =+K226 | U49: =+K227 | V49: =+K228 | W49: =+K229 | X49: =+K230 | Y49: =+K231 | Z49: =+K232 | AA49: =+K233 | AD49: 2024
A50: 40086 | B50: 13315.05 | C50: =(B50/B49-1)/(A50-A49)*30 | O50: 2025 | P50: =+K234 | Q50: =+K235 | R50: =+K236 | S50: =+K237 | T50: =+K238 | U50: =+K239 | V50: =+K240 | W50: =+K241 | X50: =+K242 | Y50: =+K243 | Z50: =+K244 | AA50: =+K245 | AD50: 2025 | AF50: =+(Q50/P50-1) | AG50: =+(R50/Q50-1) | AH50: =+(S50/R50-1) | AI50: =+(T50/S50-1) | AJ50: =+(U50/T50-1) | AK50: =+(V50/U50-1) | AL50: =+(W50/V50-1) | AM50: =+(X50/W50-1) | ... AP50: =+(AA50/Z50-1) | AQ50: =+(AA50/P50-1)/COUNTA(AE50:AP50)*12
A51: 40116 | B51: 13319.74 | C51: =(B51/B50-1)/(A51-A50)*30 | O51: 2026 | P51: =+K246 | Q51: =+K247 | R51: =+K248 | S51: =+K249 | T51: =+K250 | U51: =+K251 | AD51: 2026 | AE51: =+(P51/AA50-1) | AF51: =+(Q51/P51-1) | AG51: =+(R51/Q51-1) | AH51: =+(S51/R51-1) | AI51: =+T51/S51-1 | AJ51: =+U51/T51-1 | AQ51: =+(U51/P51-1)/COUNTA(AE51:AJ51)*12
A52: 40147 | B52: 13324.51 | C52: =(B52/B51-1)/(A52-A51)*30
A53: 40178 | B53: 13329.5 | C53: =(B53/B52-1)/(A53-A52)*30 | AD53: (*) Acum a Mar
A54: 40207 | B54: 13334.25 | C54: =(B54/B53-1)/(A54-A53)*30 | AC54: Año | AD54: Fondo | AE54: Ene | AF54: Feb | AG54: Mar | AH54: Abr | AI54: May | AJ54: Jun | AK54: Jul | AL54: Ago | AM54: Sep | AN54: Oct | AO54: Nov | AP54: Dic | AQ54: Total Año
A55: 40235 | B55: 13338.53 | C55: =(B55/B54-1)/(A55-A54)*30 | AC55: 2013 | AD55: ICP
A56: 40268 | B56: 13343.79 | C56: =(B56/B55-1)/(A56-A55)*30 | AC56: 2014 | AD56: ICP
A57: 40298 | B57: 13348.63 | C57: =(B57/B56-1)/(A57-A56)*30 | AC57: 2015 | AD57: ICP
A58: 40329 | B58: 13353.5 | C58: =(B58/B57-1)/(A58-A57)*30 | AC58: 2016 | AD58: ICP
A59: 40359 | B59: 13360.9 | C59: =(B59/B58-1)/(A59-A58)*30 | AC59: 2017 | AD59: ICP
A60: 40389 | B60: 13373.99 | C60: =(B60/B59-1)/(A60-A59)*30 | AD60: Competencia | AR60: (*)
A61: 40421 | B61: 13395.21 | C61: =(B61/B60-1)/(A61-A60)*30 | AD61: FIP Liquidez Corriente
A62: 40451 | B62: 13419.79 | C62: =(B62/B61-1)/(A62-A61)*30 | AC62: 2018 | AD62: ICP
A63: 40480 | B63: 13448.69 | C63: =(B63/B62-1)/(A63-A62)*30 | AD63: Competencia
A64: 40512 | B64: 13483.02 | C64: =(B64/B63-1)/(A64-A63)*30 | AD64: FIP Liquidez Corriente
A65: 40543 | B65: 13522.93 | C65: =(B65/B64-1)/(A65-A64)*30 | AC65: 2019 | AD65: ICP
A66: 40574 | B66: 13557.12 | C66: =(B66/B65-1)/(A66-A65)*30 | AD66: Competencia
A67: 40602 | B67: 13592.3 | C67: =(B67/B66-1)/(A67-A66)*30 | AD67: FIP Liquidez Corriente
A68: 40633 | B68: 13635.91 | C68: =(B68/B67-1)/(A68-A67)*30 | AC68: 2020 | AD68: ICP
A69: 40662 | B69: 13682.94 | C69: =(B69/B68-1)/(A69-A68)*30 | AD69: Competencia
A70: 40694 | B70: 13741.06 | C70: =(B70/B69-1)/(A70-A69)*30 | AD70: FIP Liquidez Corriente
A71: 40724 | B71: 13799.74 | C71: =(B71/B70-1)/(A71-A70)*30 | AC71: 2021 | AD71: ICP
A72: 40753 | B72: 13858.14 | C72: =(B72/B71-1)/(A72-A71)*30 | AD72: Competencia
A73: 40786 | B73: 13925.03 | C73: =(B73/B72-1)/(A73-A72)*30 | AD73: FIP Liquidez Corriente
A74: 40816 | B74: 13985.97 | C74: =(B74/B73-1)/(A74-A73)*30 | AC74: 2022 | AD74: ICP
A75: 40847 | B75: 14043.21 | C75: =(B75/B74-1)/(A75-A74)*30 | AD75: Competencia
A76: 40877 | B76: 14110.87 | C76: =(B76/B75-1)/(A76-A75)*30 | AD76: FIP Liquidez Corriente
A77: 40907 | B77: 14172.63 | C77: =(B77/B76-1)/(A77-A76)*30 | AC77: 2023 | AD77: ICP
A78: 40939 | B78: 14236.38 | C78: =(B78/B77-1)/(A78-A77)*30 | AD78: Competencia
A79: 40968 | B79: 14293.67 | C79: =(B79/B78-1)/(A79-A78)*30 | AD79: FIP Liquidez Corriente
A80: 40998 | B80: 14353.34 | C80: =(B80/B79-1)/(A80-A79)*30 | AC80: 2024 | AD80: ICP
A81: 41029 | B81: 14415.21 | C81: =(B81/B80-1)/(A81-A80)*30 | AD81: Competencia
A82: 41060 | B82: 14477.55 | C82: =(B82/B81-1)/(A82-A81)*30 | AD82: FIP Liquidez Corriente
A83: 41089 | B83: 14536.13 | C83: =(B83/B82-1)/(A83-A82)*30 | AC83: 2025 | AD83: ICP | AF83: =+AF21 | AG83: =+AG21 | AH83: =+AH21 | AI83: =+AI21 | AJ83: =+AJ21 | AK83: =+AK21 | AL83: =+AL21 | AM83: =+AM21 | ... AQ83: =+AQ21
A84: 41121 | B84: 14600.61 | C84: =(B84/B83-1)/(A84-A83)*30 | AD84: Competencia | AF84: =+AF50 | AG84: =+AG50 | AH84: =+AH50 | AI84: =+AI50 | AJ84: =+AJ50 | AK84: =+AK50 | AL84: =+AL50 | AM84: =+AM50 | ... AQ84: =+AQ50
A85: 41152 | B85: 14663.33 | C85: =(B85/B84-1)/(A85-A84)*30 | AD85: FIP Liquidez Corriente | AF85: =+AF37 | AG85: =+AG37 | AH85: =+AH37 | AI85: =+AI37 | AJ85: =+AJ37 | AK85: =+AK37 | AL85: =+AL37 | AM85: =+AM37 | ... AQ85: =+AQ37
A86: 41180 | B86: 14720.68 | C86: =(B86/B85-1)/(A86-A85)*30 | AC86: 2026 | AD86: ICP | AE86: =+AE22 | AF86: =+AF22 | AG86: =+AG22 | AH86: =+AH22 | AQ86: =+AQ22
A87: 41213 | B87: 14788.56 | C87: =(B87/B86-1)/(A87-A86)*30 | AD87: Competencia | AE87: =+AE51 | AF87: =+AF51 | AG87: =+AG51 | AH87: =+AH51 | AQ87: =+AQ51
A88: 41243 | B88: 14850.38 | C88: =(B88/B87-1)/(A88-A87)*30 | AD88: FIP Liquidez Corriente | AE88: =+AE38 | AF88: =+AF38 | AG88: =+AG38 | AH88: =+AH38 | AQ88: =+AQ38
A89: 41274 | B89: 14908.2 | C89: =(B89/B88-1)/(A89-A88)*30
A90: 41305 | B90: 14978.58 | C90: =(B90/B89-1)/(A90-A89)*30
A91: 41333 | B91: 15036.94 | C91: =(B91/B90-1)/(A91-A90)*30
A92: 41362 | B92: 15095.51 | C92: =(B92/B91-1)/(A92-A91)*30
A93: 41394 | B93: 15164.77 | C93: =(B93/B92-1)/(A93-A92)*30 | AD93: 43008 | AE93: 0.0031121
A94: 41425 | B94: 15230.38 | C94: =(B94/B93-1)/(A94-A93)*30 | AD94: 43039 | AE94: 0.0026635495
A95: 41453 | B95: 15289.74 | C95: =(B95/B94-1)/(A95-A94)*30 | AD95: 43069 | AE95: 0.0027040193
A96: 41486 | B96: 15360.27 | C96: =(B96/B95-1)/(A96-A95)*30 | AD96: 43100 | AE96: 0.0030096545
A97: 41516 | B97: 15424.43 | C97: =(B97/B96-1)/(A97-A96)*30 | AD97: 43131 | AE97: 0.0047372724
A98: 41547 | B98: 15490.99 | C98: =(B98/B97-1)/(A98-A97)*30 | AD98: 43159 | AE98: 0.003781523
A99: 41578 | B99: 15554.36 | C99: =(B99/B98-1)/(A99-A98)*30 | AD99: 43190 | AE99: 0.0030052751
A100: 41607 | B100: 15615.06 | C100: =(B100/B99-1)/(A100-A99)*30 | AD100: 43220 | AE100: 0.0031613025
...

Sheet rentabilidad
S1: Rentabilidad | T1: Mensual | U1: Trimestral | V1: Semestral | W1: Anual | X1: Acum 2026 (*)
S2: ICP (Benchmark) | T2: =+'Datos ICP (2)'!AX29 | U2: =+'Datos ICP (2)'!AY29 | V2: =+'Datos ICP (2)'!AZ29 | W2: =+Q33 | X2: =+'Datos ICP (2)'!BB29
S3: Competencia | T3: =+'Datos ICP (2)'!AX30 | U3: =+'Datos ICP (2)'!AY30 | V3: =+'Datos ICP (2)'!AZ30 | W3: =+Q34 | X3: =+'Datos ICP (2)'!BB30
S4: FIP LIQUIDEZ CORRIENTE | T4: =+'Datos ICP (2)'!AX31 | U4: =+'Datos ICP (2)'!AY31 | V4: =+'Datos ICP (2)'!AZ31 | W4: =+Q35 | X4: =+'Datos ICP (2)'!BB31
C6: Año | D6: Fondo | E6: Ene | F6: Feb | G6: Mar | H6: Abr | I6: May | J6: Jun | K6: Jul | L6: Ago | M6: Sep | N6: Oct | O6: Nov | P6: Dic | Q6: Total Año
C8: 2013 | D8: ICP
C9: 2014 | D9: ICP
C10: 2015 | D10: ICP
C11: 2016 | D11: ICP
C12: 2017 | D12: ICP
D13: Competencia
D14: FIP LIQUIDEZ Presente
C15: 2018 | D15: ICP
D16: Competencia
D17: FIP LIQUIDEZ Presente
C18: 2019 | D18: ICP
D19: Competencia
D20: FIP LIQUIDEZ Presente
C21: 2020 | D21: ICP
D22: Competencia
D23: FIP LIQUIDEZ Presente
C24: 2021 | D24: ICP
D25: Competencia
D26: FIP LIQUIDEZ Presente
C27: 2022 | D27: ICP
D28: Competencia
D29: FIP LIQUIDEZ Presente
C30: 2023 | D30: ICP
D31: Competencia
D32: FIP LIQUIDEZ Presente
C33: 2024 | D33: ICP | O33: =+'Datos ICP (2)'!AO80 | P33: =+'Datos ICP (2)'!AP80 | Q33: =+'Datos ICP (2)'!$AQ$80
D34: Competencia | O34: =+'Datos ICP (2)'!AO81 | P34: =+'Datos ICP (2)'!AP81 | Q34: =+'Datos ICP (2)'!$AQ$81
D35: FIP LIQUIDEZ CORRIENTE | O35: =+'Datos ICP (2)'!AO82 | P35: =+'Datos ICP (2)'!AP82 | Q35: =+'Datos ICP (2)'!$AQ$82
C36: 2025 | D36: ICP | E36: =+'Datos ICP (2)'!AE83 | F36: =+'Datos ICP (2)'!AF83 | G36: =+'Datos ICP (2)'!AG83 | H36: =+'Datos ICP (2)'!AH83 | I36: =+'Datos ICP (2)'!AI83 | J36: =+'Datos ICP (2)'!AJ83 | K36: =+'Datos ICP (2)'!AK83 | L36: =+'Datos ICP (2)'!AL83 | ... Q36: =+'Datos ICP (2)'!AQ83
D37: Competencia | E37: =+'Datos ICP (2)'!AE84 | F37: =+'Datos ICP (2)'!AF84 | G37: =+'Datos ICP (2)'!AG84 | H37: =+'Datos ICP (2)'!AH84 | I37: =+'Datos ICP (2)'!AI84 | J37: =+'Datos ICP (2)'!AJ84 | K37: =+'Datos ICP (2)'!AK84 | L37: =+'Datos ICP (2)'!AL84 | ... Q37: =+'Datos ICP (2)'!AQ84
D38: FIP LIQUIDEZ CORRIENTE | E38: =+'Datos ICP (2)'!AE85 | F38: =+'Datos ICP (2)'!AF85 | G38: =+'Datos ICP (2)'!AG85 | H38: =+'Datos ICP (2)'!AH85 | I38: =+'Datos ICP (2)'!AI85 | J38: =+'Datos ICP (2)'!AJ85 | K38: =+'Datos ICP (2)'!AK85 | L38: =+'Datos ICP (2)'!AL85 | ... Q38: =+'Datos ICP (2)'!AQ85
C39: 2026 | D39: ICP | E39: =+'Datos ICP (2)'!AE86 | F39: =+'Datos ICP (2)'!AF86 | G39: =+'Datos ICP (2)'!AG86 | H39: =+'Datos ICP (2)'!AH86 | Q39: =+'Datos ICP (2)'!AQ86
D40: Competencia | E40: =+'Datos ICP (2)'!AE87 | F40: =+'Datos ICP (2)'!AF87 | G40: =+'Datos ICP (2)'!AG87 | H40: =+'Datos ICP (2)'!AH87 | Q40: =+'Datos ICP (2)'!AQ87
D41: FIP LIQUIDEZ CORRIENTE | E41: =+'Datos ICP (2)'!AE88 | F41: =+'Datos ICP (2)'!AF88 | G41: =+'Datos ICP (2)'!AG88 | H41: =+'Datos ICP (2)'!AH88 | Q41: =+'Datos ICP (2)'!AQ88

Sheet composición
J1: Duración | N1: Instrumentos | R1: Moneda
O2: Bono | P2: 0
K3: Menos de 1 mes | L3: 0.2228 | O3: Depósitos | P3: 0 | S3: Pesos | T3: 1
K4: 1-3 meses | L4: 0.4666 | O4: Factoring | P4: 0 | S4: UF | T4: 0
K5: 3-4 meses | L5: 0.3106 | O5: Financiamiento Inmobiliario | P5: 0.2617
K6: Más de 4 meses | L6: 0 | O6: Financiamiento Mesa Moneda Extranjera | P6: 0.6388
L7: =SUM(L3:L6) | O7: Garantías | P7: 0.0995
O8: Nota Estructurada | P8: 0
O9: Financiamiento Mesa Renta Fija | P9: 0
O10: Simultánea | P10: 0
O11: Efectos de Comercio | P11: 0
O13: Pagaré | P13: 0
A14: Facturas | B14: 0
P15: =SUM(P2:P14)
