Workbook
Name OLE_LINK1: 'Datos ICP (2)'!#REF!

Sheet Comentario
A2: El IPC de abril en Estados Unidos sorprendió levemente al alza respecto de las expectativas, impulsado principalmente por el fuerte aumento de los precios de la energía. La gasolina explicó una parte importante del avance del índice general, mientras que la inflación subyacente también mostró resiliencia, explicada en parte por un ajuste en los precios de arriendos tras las distorsiones asociadas al cierre parcial del gobierno el año pasado. El IPC general registró un aumento de 0,6% mensual, llevando la inflación anual a 3,8%, su mayor nivel en tres años. Por su parte, la inflación subyacente avanzó 0,4% mensual, impulsada por mayores costos de vivienda, particularmente en el componente equivalente de arriendo y arriendos efectivos. Por su parte, las nóminas no agrícolas aumentaron en 115 mil puestos durante abril, mientras que la tasa de desempleo se mantuvo estable en 4,3%, evidenciando un mercado laboral aún sólido. Por su parte, la Reserva Federal mantuvo una postura cautelosa respecto de la política monetaria, monitoreando tanto la persistencia de la inflación subyacente como los riesgos derivados del conflicto geopolítico y su impacto sobre los precios de la energía.

Sheet Datos ICP (2)
A1: CLICP Index | F1: Cuota LIQUIDEZ RESERVA DÓLAR | AD1: ICP | AE1: Ene | AF1: Feb | AG1: Mar | AH1: Abr | AI1: May | AJ1: Jun | AK1: Jul | AL1: Ago | AM1: Sep | AN1: Oct | AO1: Nov | AP1: Dic | AQ1: Total Año
A2: Fecha | B2: ICP | D2: ICP Norm. | J2: FondoLiquidez Reserva Dólar | K2: 8248-1 | M2: Competencia (*) | P2: Ene | Q2: Feb | R2: Mar | S2: Abr | T2: May | U2: Jun | V2: Jul | W2: Ago | X2: Sep | Y2: Oct | Z2: Nov | AA2: Dic | AD2: 2006 | AE2: =+P3 | AF2: =+Q3 | AG2: =+R3 | AH2: =+S3 | AI2: =+T3 | AJ2: =+U3 | AK2: =+V3 | AL2: =+W3 | ... AP2: =+AA3 | AQ2: =+B16/B3-1
A3: 38717 | B3: 10953.14 | D3: =B3/$B$3*100 | N3: =B3 | O3: 2006 | P3: =LOOKUP(DATE($O3,P$25,P$24),$A$2:$A$2943,$C$2:$C$2943) | Q3: =LOOKUP(DATE($O3,Q$25,Q$24),$A$2:$A$2943,$C$2:$C$2943) | R3: =LOOKUP(DATE($O3,R$25,R$24),$A$2:$A$2943,$C$2:$C$2943) | S3: =LOOKUP(DATE($O3,S$25,S$24),$A$2:$A$2943,$C$2:$C$2943) | T3: =LOOKUP(DATE($O3,T$25,T$24),$A$2:$A$2943,$C$2:$C$2943) | U3: =LOOKUP(DATE($O3,U$25,U$24),$A$2:$A$2943,$C$2:$C$2943) | V3: =LOOKUP(DATE($O3,V$25,V$24),$A$2:$A$2943,$C$2:$C$2943) | W3: =LOOKUP(DATE($O3,W$25,W$24),$A$2:$A$2943,$C$2:$C$2943) | ... AA3: =LOOKUP(DATE($O3,AA$25,AA$24),$A$2:$A$2943,$C$2:$C$2943) | AD3: 2007 | AE3: =+P4 | AF3: =+Q4 | AG3: =+R4 | AH3: =+S4 | AI3: =+T4 | AJ3: =+U4 | AK3: =+V4 | AL3: =+W4 | ... AP3: =+AA4 | AQ3: =+B28/B15-1
A4: 38748 | B4: 10996.85 | C4: =(B4/B3-1)/(A4-A3)*360 | D4: =B4/$B$3*100 | K4: Corporate Dollar Serie A Banchile | O4: 2007 | P4: =LOOKUP(DATE($O4,P$25,P$24),$A$2:$A$2943,$C$2:$C$2943) | Q4: =LOOKUP(DATE($O4,Q$25,Q$24),$A$2:$A$2943,$C$2:$C$2943) | R4: =LOOKUP(DATE($O4,R$25,R$24),$A$2:$A$2943,$C$2:$C$2943) | S4: =LOOKUP(DATE($O4,S$25,S$24),$A$2:$A$2943,$C$2:$C$2943) | T4: =LOOKUP(DATE($O4,T$25,T$24),$A$2:$A$2943,$C$2:$C$2943) | U4: =LOOKUP(DATE($O4,U$25,U$24),$A$2:$A$2943,$C$2:$C$2943) | V4: =LOOKUP(DATE($O4,V$25,V$24),$A$2:$A$2943,$C$2:$C$2943) | W4: =LOOKUP(DATE($O4,W$25,W$24),$A$2:$A$2943,$C$2:$C$2943) | ... AA4: =LOOKUP(DATE($O4,AA$25,AA$24),$A$2:$A$2943,$C$2:$C$2943) | AD4: 2008 | AE4: =+P5 | AF4: =+Q5 | AG4: =+R5 | AH4: =+S5 | AI4: =+T5 | AJ4: =+U5 | AK4: =+V5 | AL4: =+W5 | ... AP4: =+AA5 | AQ4: =+B41/B29-1
A5: 38776 | B5: 11035.11 | C5: =(B5/B4-1)/(A5-A4)*360 | D5: =B5/$B$3*100 | O5: 2008 | P5: =LOOKUP(DATE($O5,P$25,P$24),$A$2:$A$2943,$C$2:$C$2943) | Q5: =LOOKUP(DATE($O5,Q$25,Q$24),$A$2:$A$2943,$C$2:$C$2943) | R5: =LOOKUP(DATE($O5,R$25,R$24),$A$2:$A$2943,$C$2:$C$2943) | S5: =LOOKUP(DATE($O5,S$25,S$24),$A$2:$A$2943,$C$2:$C$2943) | T5: =LOOKUP(DATE($O5,T$25,T$24),$A$2:$A$2943,$C$2:$C$2943) | U5: =LOOKUP(DATE($O5,U$25,U$24),$A$2:$A$2943,$C$2:$C$2943) | V5: =LOOKUP(DATE($O5,V$25,V$24),$A$2:$A$2943,$C$2:$C$2943) | W5: =LOOKUP(DATE($O5,W$25,W$24),$A$2:$A$2943,$C$2:$C$2943) | ... AA5: =LOOKUP(DATE($O5,AA$25,AA$24),$A$2:$A$2943,$C$2:$C$2943) | AD5: 2009 | AE5: =+P6 | AF5: =+Q6 | AG5: =+R6 | AH5: =+S6 | AI5: =+T6 | AJ5: =+U6 | AK5: =+V6 | AL5: =+W6 | ... AP5: =+AA6 | AQ5: =+B53/B41-1
A6: 38807 | B6: 11078.66 | C6: =(B6/B5-1)/(A6-A5)*360 | D6: =B6/$B$3*100 | O6: 2009 | P6: =LOOKUP(DATE($O6,P$25,P$24),$A$2:$A$2943,$C$2:$C$2943) | Q6: =LOOKUP(DATE($O6,Q$25,Q$24),$A$2:$A$2943,$C$2:$C$2943) | R6: =LOOKUP(DATE($O6,R$25,R$24),$A$2:$A$2943,$C$2:$C$2943) | S6: =LOOKUP(DATE($O6,S$25,S$24),$A$2:$A$2943,$C$2:$C$2943) | T6: =LOOKUP(DATE($O6,T$25,T$24),$A$2:$A$2943,$C$2:$C$2943) | U6: =LOOKUP(DATE($O6,U$25,U$24),$A$2:$A$2943,$C$2:$C$2943) | V6: =LOOKUP(DATE($O6,V$25,V$24),$A$2:$A$2943,$C$2:$C$2943) | W6: =LOOKUP(DATE($O6,W$25,W$24),$A$2:$A$2943,$C$2:$C$2943) | ... AA6: =LOOKUP(DATE($O6,AA$25,AA$24),$A$2:$A$2943,$C$2:$C$2943) | AD6: 2010 | AE6: =+P7 | AF6: =+Q7 | AG6: =+R7 | AH6: =+S7 | AI6: =+T7 | AJ6: =+U7 | AK6: =+V7 | AL6: =+W7 | ... AP6: =+AA7 | AQ6: =+B65/B53-1
A7: 38835 | B7: 11118.82 | C7: =(B7/B6-1)/(A7-A6)*360 | D7: =B7/$B$3*100 | O7: 2010 | P7: =LOOKUP(DATE($O7,P$25,P$24),$A$2:$A$2943,$C$2:$C$2943) | Q7: =LOOKUP(DATE($O7,Q$25,Q$24),$A$2:$A$2943,$C$2:$C$2943) | R7: =LOOKUP(DATE($O7,R$25,R$24),$A$2:$A$2943,$C$2:$C$2943) | S7: =LOOKUP(DATE($O7,S$25,S$24),$A$2:$A$2943,$C$2:$C$2943) | T7: =LOOKUP(DATE($O7,T$25,T$24),$A$2:$A$2943,$C$2:$C$2943) | U7: =LOOKUP(DATE($O7,U$25,U$24),$A$2:$A$2943,$C$2:$C$2943) | V7: =LOOKUP(DATE($O7,V$25,V$24),$A$2:$A$2943,$C$2:$C$2943) | W7: =LOOKUP(DATE($O7,W$25,W$24),$A$2:$A$2943,$C$2:$C$2943) | ... AA7: =LOOKUP(DATE($O7,AA$25,AA$24),$A$2:$A$2943,$C$2:$C$2943) | AD7: 2011 | AE7: =+P8 | AF7: =+Q8 | AG7: =+R8 | AH7: =+S8 | AI7: =+T8 | AJ7: =+U8 | AK7: =+V8 | AL7: =+W8 | ... AP7: =+AA8 | AQ7: =+B77/B65-1
A8: 38868 | B8: 11169.1 | C8: =(B8/B7-1)/(A8-A7)*360 | D8: =B8/$B$3*100 | O8: 2011 | P8: =LOOKUP(DATE($O8,P$25,P$24),$A$2:$A$2943,$C$2:$C$2943) | Q8: =LOOKUP(DATE($O8,Q$25,Q$24),$A$2:$A$2943,$C$2:$C$2943) | R8: =LOOKUP(DATE($O8,R$25,R$24),$A$2:$A$2943,$C$2:$C$2943) | S8: =LOOKUP(DATE($O8,S$25,S$24),$A$2:$A$2943,$C$2:$C$2943) | T8: =LOOKUP(DATE($O8,T$25,T$24),$A$2:$A$2943,$C$2:$C$2943) | U8: =LOOKUP(DATE($O8,U$25,U$24),$A$2:$A$2943,$C$2:$C$2943) | V8: =LOOKUP(DATE($O8,V$25,V$24),$A$2:$A$2943,$C$2:$C$2943) | W8: =LOOKUP(DATE($O8,W$25,W$24),$A$2:$A$2943,$C$2:$C$2943) | ... AA8: =LOOKUP(DATE($O8,AA$25,AA$24),$A$2:$A$2943,$C$2:$C$2943) | AD8: 2012 | AE8: =+P9 | AF8: =+Q9 | AG8: =+R9 | AH8: =+S9 | AI8: =+T9 | AJ8: =+U9 | AK8: =+V9 | AL8: =+W9 | ... AP8: =+AA9 | AQ8: =+B89/B78-1
A9: 38898 | B9: 11215.04 | C9: =(B9/B8-1)/(A9-A8)*360 | D9: =B9/$B$3*100 | O9: 2012 | P9: =LOOKUP(DATE($O9,P$25,P$24),$A$2:$A$2943,$C$2:$C$2943) | Q9: =LOOKUP(DATE($O9,Q$25,Q$24),$A$2:$A$2943,$C$2:$C$2943) | R9: =LOOKUP(DATE($O9,R$25,R$24),$A$2:$A$2943,$C$2:$C$2943) | S9: =LOOKUP(DATE($O9,S$25,S$24),$A$2:$A$2943,$C$2:$C$2943) | T9: =LOOKUP(DATE($O9,T$25,T$24),$A$2:$A$2943,$C$2:$C$2943) | U9: =LOOKUP(DATE($O9,U$25,U$24),$A$2:$A$2943,$C$2:$C$2943) | V9: =LOOKUP(DATE($O9,V$25,V$24),$A$2:$A$2943,$C$2:$C$2943) | W9: =LOOKUP(DATE($O9,W$25,W$24),$A$2:$A$2943,$C$2:$C$2943) | ... AA9: =LOOKUP(DATE($O9,AA$25,AA$24),$A$2:$A$2943,$C$2:$C$2943) | AD9: 2013 | AE9: =+P10 | AF9: =+Q10 | AG9: =+R10 | AH9: =+S10 | AI9: =+T10 | AJ9: =+U10 | AK9: =+V10 | AL9: =+W10 | ... AP9: =+AA10 | AQ9: =+B101/B89-1
A10: 38929 | B10: 11263.22 | C10: =(B10/B9-1)/(A10-A9)*360 | D10: =B10/$B$3*100 | O10: 2013 | P10: =LOOKUP(DATE($O10,P$25,P$24),$A$2:$A$2943,$C$2:$C$2943) | Q10: =LOOKUP(DATE($O10,Q$25,Q$24),$A$2:$A$2943,$C$2:$C$2943) | R10: =LOOKUP(DATE($O10,R$25,R$24),$A$2:$A$2943,$C$2:$C$2943) | S10: =LOOKUP(DATE($O10,S$25,S$24),$A$2:$A$2943,$C$2:$C$2943) | T10: =LOOKUP(DATE($O10,T$25,T$24),$A$2:$A$2943,$C$2:$C$2943) | U10: =LOOKUP(DATE($O10,U$25,U$24),$A$2:$A$2943,$C$2:$C$2943) | V10: =LOOKUP(DATE($O10,V$25,V$24),$A$2:$A$2943,$C$2:$C$2943) | W10: =LOOKUP(DATE($O10,W$25,W$24),$A$2:$A$2943,$C$2:$C$2943) | ... AA10: =LOOKUP(DATE($O10,AA$25,AA$24),$A$2:$A$2943,$C$2:$C$2943) | AD10: 2014 | AE10: =+P11 | AF10: =+Q11 | AG10: =+R11 | AH10: =+S11 | AI10: =+T11 | AJ10: =+U11 | AK10: =+V11 | AL10: =+W11 | ... AP10: =+AA11 | AQ10: =+B113/B102-1
A11: 38960 | B11: 11313.29 | C11: =(B11/B10-1)/(A11-A10)*360 | D11: =B11/$B$3*100 | O11: 2014 | P11: =LOOKUP(DATE($O11,P$25,P$24),$A$2:$A$2943,$C$2:$C$2943) | Q11: =LOOKUP(DATE($O11,Q$25,Q$24),$A$2:$A$2943,$C$2:$C$2943) | R11: =LOOKUP(DATE($O11,R$25,R$24),$A$2:$A$2943,$C$2:$C$2943) | S11: =LOOKUP(DATE($O11,S$25,S$24),$A$2:$A$2943,$C$2:$C$2943) | T11: =LOOKUP(DATE($O11,T$25,T$24),$A$2:$A$2943,$C$2:$C$2943) | U11: =LOOKUP(DATE($O11,U$25,U$24),$A$2:$A$2943,$C$2:$C$2943) | V11: =LOOKUP(DATE($O11,V$25,V$24),$A$2:$A$2943,$C$2:$C$2943) | W11: =LOOKUP(DATE($O11,W$25,W$24),$A$2:$A$2943,$C$2:$C$2943) | ... AA11: =LOOKUP(DATE($O11,AA$25,AA$24),$A$2:$A$2943,$C$2:$C$2943) | AD11: 2015 | AE11: =+P12 | AF11: =+Q12 | AG11: =+R12 | AH11: =+S12 | AI11: =+T12 | AJ11: =+U12 | AK11: =+V12 | AL11: =+W12 | ... AP11: =+AA12 | AQ11: =+B125/B113-1
A12: 38989 | B12: 11360.92 | C12: =(B12/B11-1)/(A12-A11)*360 | D12: =B12/$B$3*100 | O12: 2015 | P12: =LOOKUP(DATE($O12,P$25,P$24),$A$2:$A$2943,$C$2:$C$2943) | Q12: =LOOKUP(DATE($O12,Q$25,Q$24),$A$2:$A$2943,$C$2:$C$2943) | R12: =LOOKUP(DATE($O12,R$25,R$24),$A$2:$A$2943,$C$2:$C$2943) | S12: =LOOKUP(DATE($O12,S$25,S$24),$A$2:$A$2943,$C$2:$C$2943) | T12: =LOOKUP(DATE($O12,T$25,T$24),$A$2:$A$2943,$C$2:$C$2943) | U12: =LOOKUP(DATE($O12,U$25,U$24),$A$2:$A$2943,$C$2:$C$2943) | V12: =LOOKUP(DATE($O12,V$25,V$24),$A$2:$A$2943,$C$2:$C$2943) | W12: =LOOKUP(DATE($O12,W$25,W$24),$A$2:$A$2943,$C$2:$C$2943) | ... AA12: =LOOKUP(DATE($O12,AA$25,AA$24),$A$2:$A$2943,$C$2:$C$2943) | AD12: 2016 | AE12: =+P13 | AF12: =+Q13 | AG12: =+R13 | AH12: =+S13 | AI12: =+T13 | AJ12: =+U13 | AK12: =+V13 | AL12: =+W13 | ... AP12: =+AA13 | AQ12: =+B137/B125-1
A13: 39021 | B13: 11413.02 | C13: =(B13/B12-1)/(A13-A12)*360 | D13: =B13/$B$3*100 | O13: 2016 | P13: =LOOKUP(DATE($O13,P$25,P$24),$A$2:$A$2943,$C$2:$C$2943) | Q13: =LOOKUP(DATE($O13,Q$25,Q$24),$A$2:$A$2943,$C$2:$C$2943) | R13: =LOOKUP(DATE($O13,R$25,R$24),$A$2:$A$2943,$C$2:$C$2943) | S13: =LOOKUP(DATE($O13,S$25,S$24),$A$2:$A$2943,$C$2:$C$2943) | T13: =LOOKUP(DATE($O13,T$25,T$24),$A$2:$A$2943,$C$2:$C$2943) | U13: =LOOKUP(DATE($O13,U$25,U$24),$A$2:$A$2943,$C$2:$C$2943) | V13: =LOOKUP(DATE($O13,V$25,V$24),$A$2:$A$2943,$C$2:$C$2943) | W13: =LOOKUP(DATE($O13,W$25,W$24),$A$2:$A$2943,$C$2:$C$2943) | ... AA13: =LOOKUP(DATE($O13,AA$25,AA$24),$A$2:$A$2943,$C$2:$C$2943) | AD13: 2017 | AE13: =+P14 | AF13: =+Q14 | AG13: =+R14 | AH13: =+S14 | AI13: =+T14 | AJ13: =+U14 | AK13: =+V14 | AL13: =+W14 | ... AP13: =+AA14 | AQ13: =+B149/B137-1
A14: 39051 | B14: 11463.01 | C14: =(B14/B13-1)/(A14-A13)*360 | D14: =B14/$B$3*100 | O14: 2017 | P14: =LOOKUP(DATE($O14,P$25,P$24),$A$2:$A$2943,$C$2:$C$2943) | Q14: =LOOKUP(DATE($O14,Q$25,Q$24),$A$2:$A$2943,$C$2:$C$2943) | R14: =LOOKUP(DATE($O14,R$25,R$24),$A$2:$A$2943,$C$2:$C$2943) | S14: =LOOKUP(DATE($O14,S$25,S$24),$A$2:$A$2943,$C$2:$C$2943) | T14: =LOOKUP(DATE($O14,T$25,T$24),$A$2:$A$2943,$C$2:$C$2943) | U14: =LOOKUP(DATE($O14,U$25,U$24),$A$2:$A$2943,$C$2:$C$2943) | V14: =LOOKUP(DATE($O14,V$25,V$24),$A$2:$A$2943,$C$2:$C$2943) | W14: =LOOKUP(DATE($O14,W$25,W$24),$A$2:$A$2943,$C$2:$C$2943) | ... AA14: =LOOKUP(DATE($O14,AA$25,AA$24),$A$2:$A$2943,$C$2:$C$2943) | AD14: 2018 | AE14: =+P15 | AF14: =+Q15 | AG14: =+R15 | AH14: =+S15 | AI14: =+T15 | AJ14: =+U15 | AK14: =+V15 | AL14: =+W15 | ... AP14: =+AA15 | AQ14: =+B161/B149-1
A15: 39080 | B15: 11512.49 | C15: =(B15/B14-1)/(A15-A14)*360 | D15: =B15/$B$3*100 | O15: 2018 | P15: =LOOKUP(DATE($O15,P$25,P$24),$A$2:$A$2943,$C$2:$C$2943) | Q15: =LOOKUP(DATE($O15,Q$25,Q$24),$A$2:$A$2943,$C$2:$C$2943) | R15: =LOOKUP(DATE($O15,R$25,R$24),$A$2:$A$2943,$C$2:$C$2943) | S15: =LOOKUP(DATE($O15,S$25,S$24),$A$2:$A$2943,$C$2:$C$2943) | T15: =LOOKUP(DATE($O15,T$25,T$24),$A$2:$A$2943,$C$2:$C$2943) | U15: =LOOKUP(DATE($O15,U$25,U$24),$A$2:$A$2943,$C$2:$C$2943) | V15: =LOOKUP(DATE($O15,V$25,V$24),$A$2:$A$2943,$C$2:$C$2943) | W15: =LOOKUP(DATE($O15,W$25,W$24),$A$2:$A$2943,$C$2:$C$2943) | ... AA15: =LOOKUP(DATE($O15,AA$25,AA$24),$A$2:$A$2943,$C$2:$C$2943) | AD15: 2019 | AE15: =+P16 | AF15: =+Q16 | AG15: =+R16 | AH15: =+S16 | AI15: =+T16 | AJ15: =+U16 | AK15: =+V16 | AL15: =+W16 | ... AP15: =+AA16 | AQ15: =+(B173/B161-1)/COUNTA(AE15:AP15)*12 | AR15: (*)
A16: 39113 | B16: 11567.23 | C16: =(B16/B15-1)/(A16-A15)*360 | D16: =B16/$B$3*100 | O16: 2019 | P16: =LOOKUP(DATE($O16,P$25,P$24),$A$2:$A$2943,$C$2:$C$2943) | Q16: =LOOKUP(DATE($O16,Q$25,Q$24),$A$2:$A$2943,$C$2:$C$2943) | R16: =LOOKUP(DATE($O16,R$25,R$24),$A$2:$A$2943,$C$2:$C$2943) | S16: =LOOKUP(DATE($O16,S$25,S$24),$A$2:$A$2943,$C$2:$C$2943) | T16: =LOOKUP(DATE($O16,T$25,T$24),$A$2:$A$2943,$C$2:$C$2943) | U16: =LOOKUP(DATE($O16,U$25,U$24),$A$2:$A$2943,$C$2:$C$2943) | V16: =LOOKUP(DATE($O16,V$25,V$24),$A$2:$A$2943,$C$2:$C$2943) | W16: =LOOKUP(DATE($O16,W$25,W$24),$A$2:$A$2943,$C$2:$C$2943) | ... AA16: =LOOKUP(DATE($O16,AA$25,AA$24),$A$2:$A$2943,$C$2:$C$2943) | AD16: 2020 | AE16: =+P17 | AF16: =+Q17 | AG16: =+R17 | AH16: =+S17 | AI16: =+T17 | AJ16: =+U17 | AK16: =+V17 | AL16: =+W17 | ... AP16: =+AA17 | AQ16: =+(B185/B173-1)/COUNTA(AE16:AP16)*12
A17: 39141 | B17: 11612.68 | C17: =(B17/B16-1)/(A17-A16)*360 | D17: =B17/$B$3*100 | O17: 2020 | P17: =LOOKUP(DATE($O17,P$25,P$24),$A$2:$A$2943,$C$2:$C$2943) | Q17: =LOOKUP(DATE($O17,Q$25,Q$24)+1,$A$2:$A$2943,$C$2:$C$2943) | R17: =LOOKUP(DATE($O17,R$25,R$24),$A$2:$A$2943,$C$2:$C$2943) | S17: =LOOKUP(DATE($O17,S$25,S$24),$A:$A,$C:$C) | T17: =LOOKUP(DATE($O17,T$25,T$24),$A:$A,$C:$C) | U17: =LOOKUP(DATE($O17,U$25,U$24),$A:$A,$C:$C) | V17: =LOOKUP(DATE($O17,V$25,V$24),$A:$A,$C:$C) | W17: =LOOKUP(DATE($O17,W$25,W$24),$A:$A,$C:$C) | X17: =LOOKUP(DATE($O17,X$25,X$24),$A:$A,$C:$C) | Y17: =LOOKUP(DATE($O17,Y$25,Y$24),$A:$A,$C:$C) | Z17: =LOOKUP(DATE($O17,Z$25,Z$24),$A:$A,$C:$C) | AA17: =LOOKUP(DATE($O17,AA$25,AA$24),$A:$A,$C:$C) | AD17: 2021 | AE17: =+P18 | AF17: =+Q18 | AG17: =+R18 | AH17: =+S18 | AI17: =+T18 | AJ17: =+U18 | AK17: =+V18 | AL17: =+W18 | ... AP17: =+AA18 | AQ17: =+(B197/B185-1)/COUNTA(AE17:AP17)*12
A18: 39171 | B18: 11661.5 | C18: =(B18/B17-1)/(A18-A17)*360 | D18: =B18/$B$3*100 | O18: 2021 | P18: =LOOKUP(DATE($O18,P$25,P$24),$A$2:$A$2943,$C$2:$C$2943) | Q18: =LOOKUP(DATE($O18,Q$25,Q$24)+1,$A$2:$A$2943,$C$2:$C$2943) | R18: =LOOKUP(DATE($O18,R$25,R$24),$A$2:$A$2943,$C$2:$C$2943) | S18: =LOOKUP(DATE($O18,S$25,S$24),$A:$A,$C:$C) | T18: =LOOKUP(DATE($O18,T$25,T$24),$A:$A,$C:$C) | U18: =LOOKUP(DATE($O18,U$25,U$24),$A:$A,$C:$C) | V18: =LOOKUP(DATE($O18,V$25,V$24),$A:$A,$C:$C) | W18: =LOOKUP(DATE($O18,W$25,W$24),$A:$A,$C:$C) | X18: =LOOKUP(DATE($O18,X$25,X$24),$A:$A,$C:$C) | Y18: =LOOKUP(DATE($O18,Y$25,Y$24),$A:$A,$C:$C) | Z18: =LOOKUP(DATE($O18,Z$25,Z$24),$A:$A,$C:$C) | AA18: =LOOKUP(DATE($O18,AA$25,AA$24),$A:$A,$C:$C) | AD18: 2022 | AE18: =+P19 | AF18: =+Q19 | AG18: =+R19 | AH18: =+S19 | AI18: =+T19 | AJ18: =+U19 | AK18: =+V19 | AL18: =+W19 | ... AP18: =+AA19 | AQ18: =+(B209/B197-1)/COUNTA(AE18:AP18)*12 | AX18: -1 | AY18: -3 | AZ18: -6 | BA18: -12
A19: 39202 | B19: 11712.58 | C19: =(B19/B18-1)/(A19-A18)*360 | D19: =B19/$B$3*100 | O19: 2022 | P19: =LOOKUP(DATE($O19,P$25,P$24),$A$2:$A$2943,$C$2:$C$2943) | Q19: =LOOKUP(DATE($O19,Q$25,Q$24),$A$2:$A$2943,$C$2:$C$2943) | R19: =LOOKUP(DATE($O19,R$25,R$24),$A$2:$A$2943,$C$2:$C$2943) | S19: =LOOKUP(DATE($O19,S$25,S$24),$A$2:$A$2943,$C$2:$C$2943) | T19: =LOOKUP(DATE($O19,T$25,T$24),$A$2:$A$2943,$C$2:$C$2943) | U19: =LOOKUP(DATE($O19,U$25,U$24),$A$2:$A$2943,$C$2:$C$2943) | V19: =LOOKUP(DATE($O19,V$25,V$24),$A$2:$A$2943,$C$2:$C$2943) | W19: =LOOKUP(DATE($O19,W$25,W$24),$A$2:$A$2943,$C$2:$C$2943) | ... AA19: =LOOKUP(DATE($O19,AA$25,AA$24),$A$2:$A$2943,$C$2:$C$2943) | AD19: 2023 | AE19: =+P20 | AF19: =+Q20 | AG19: =+R20 | AH19: =+S20 | AI19: =+T20 | AJ19: =+U20 | AK19: =+V20 | AL19: =+W20 | ... AP19: =+AA20 | AQ19: =+(B221/B209-1)/COUNTA(AE19:AP19)*12 | AV19: Ingresar mes actual==> | AW19: 46203 | AX19: =EOMONTH($AW19,AX18) | AY19: =EOMONTH($AW19,AY18) | AZ19: =EOMONTH($AW19,AZ18) | BA19: =EOMONTH($AW19,BA18) | BB19: 43100
A20: 39233 | B20: 11763.78 | C20: =(B20/B19-1)/(A20-A19)*360 | D20: =B20/$B$3*100 | O20: 2023 | P20: =LOOKUP(DATE($O20,P$25,P$24),$A$2:$A$2943,$C$2:$C$2943) | Q20: =LOOKUP(DATE($O20,Q$25,Q$24),$A$2:$A$2943,$C$2:$C$2943) | R20: =LOOKUP(DATE($O20,R$25,R$24),$A$2:$A$2943,$C$2:$C$2943) | S20: =LOOKUP(DATE($O20,S$25,S$24),$A$2:$A$2943,$C$2:$C$2943) | T20: =LOOKUP(DATE($O20,T$25,T$24),$A$2:$A$2943,$C$2:$C$2943) | U20: =LOOKUP(DATE($O20,U$25,U$24),$A$2:$A$2943,$C$2:$C$2943) | V20: =LOOKUP(DATE($O20,V$25,V$24),$A$2:$A$2943,$C$2:$C$2943) | W20: =LOOKUP(DATE($O20,W$25,W$24),$A$2:$A$2943,$C$2:$C$2943) | ... AA20: =LOOKUP(DATE($O20,AA$25,AA$24),$A$2:$A$2943,$C$2:$C$2943) | AD20: 2024 | AE20: =+P21 | AF20: =+Q21 | AG20: =+R21 | AH20: =+S21 | AI20: =+T21 | AJ20: =+U21 | AK20: =+V21 | AL20: =+W21 | ... AP20: =+AA21 | AQ20: =+(B233/B221-1)/COUNTA(AE20:AP20)*12 | AV20: Competencia | AW20: =LOOKUP(AW19,$F$2:$F$2974,$K$2:$K$2974) | AX20: =LOOKUP(AX19,$F$2:$F$2974,$K$2:$K$2974) | AY20: =LOOKUP(AY19,$F$2:$F$2974,$K$2:$K$2974) | AZ20: =LOOKUP(AZ19,$F$2:$F$2974,$K$2:$K$2974) | BA20: =LOOKUP(BA19,$F$2:$F$2974,$K$2:$K$2974) | BB20: =LOOKUP(BB19,$F$2:$F$2974,$K$2:$K$2974)
A21: 39262 | B21: 11812.23 | C21: =(B21/B20-1)/(A21-A20)*360 | D21: =B21/$B$3*100 | O21: 2024 | P21: =LOOKUP(DATE($O21,P$25,P$24),$A$2:$A$2943,$C$2:$C$2943) | Q21: =LOOKUP(DATE($O21,Q$25,Q$24),$A$2:$A$2943,$C$2:$C$2943) | R21: =LOOKUP(DATE($O21,R$25,R$24),$A$2:$A$2943,$C$2:$C$2943) | S21: =LOOKUP(DATE($O21,S$25,S$24),$A$2:$A$2943,$C$2:$C$2943) | T21: =LOOKUP(DATE($O21,T$25,T$24),$A$2:$A$2943,$C$2:$C$2943) | U21: =LOOKUP(DATE($O21,U$25,U$24),$A$2:$A$2943,$C$2:$C$2943) | V21: =LOOKUP(DATE($O21,V$25,V$24),$A$2:$A$2943,$C$2:$C$2943) | W21: =LOOKUP(DATE($O21,W$25,W$24),$A$2:$A$2943,$C$2:$C$2943) | ... AA21: =LOOKUP(DATE($O21,AA$25,AA$24),$A$2:$A$2943,$C$2:$C$2943) | AD21: 2025 | AE21: =+P22 | AF21: =+Q22 | AG21: =+R22 | AH21: =+S22 | AI21: =+T22 | AJ21: =+U22 | AK21: =+V22 | AL21: =+W22 | ... AP21: =+AA22 | AQ21: =+(B245/B234-1)/COUNTA(AE21:AP21)*12 | AV21: LIQUIDEZ RESERVA DÓLAR | AW21: =LOOKUP(AW19,$F$2:$F$2972,$H$2:$H$2972) | AX21: =LOOKUP(AX19,$F$2:$F$2972,$H$2:$H$2972) | AY21: =LOOKUP(AY19,$F$2:$F$2972,$H$2:$H$2972) | AZ21: =LOOKUP(AZ19,$F$2:$F$2972,$H$2:$H$2972) | BA21: =LOOKUP(BA19,$F$2:$F$2972,$H$2:$H$2972) | BB21: =LOOKUP(BB19,$F$2:$F$2972,$H$2:$H$2972)
A22: 39294 | B22: 11866.53 | C22: =(B22/B21-1)/(A22-A21)*360 | D22: =B22/$B$3*100 | O22: 2025 | P22: =LOOKUP(DATE($O22,P$25,P$24),$A$2:$A$2943,$C$2:$C$2943) | Q22: =LOOKUP(DATE($O22,Q$25,Q$24),$A$2:$A$2943,$C$2:$C$2943) | R22: =LOOKUP(DATE($O22,R$25,R$24),$A$2:$A$2943,$C$2:$C$2943) | S22: =LOOKUP(DATE($O22,S$25,S$24),$A$2:$A$2943,$C$2:$C$2943) | T22: =LOOKUP(DATE($O22,T$25,T$24),$A$2:$A$2943,$C$2:$C$2943) | U22: =LOOKUP(DATE($O22,U$25,U$24),$A$2:$A$2943,$C$2:$C$2943) | V22: =LOOKUP(DATE($O22,V$25,V$24),$A$2:$A$2943,$C$2:$C$2943) | W22: =LOOKUP(DATE($O22,W$25,W$24),$A$2:$A$2943,$C$2:$C$2943) | ... AA22: =LOOKUP(DATE($O22,AA$25,AA$24),$A$2:$A$2943,$C$2:$C$2943) | AD22: 2026 | AE22: =+P23 | AF22: =+Q23 | AG22: =+R23 | AH22: =+S23 | AQ22: =+(B249/B246-1)/COUNTA(AE22:AP22)*12
O23: 2026 | P23: =LOOKUP(DATE($O23,P$25,P$24),$A$2:$A$2943,$C$2:$C$2943) | Q23: =LOOKUP(DATE($O23,Q$25,Q$24),$A$2:$A$2943,$C$2:$C$2943) | R23: =LOOKUP(DATE($O23,R$25,R$24),$A$2:$A$2943,$C$2:$C$2943) | S23: =LOOKUP(DATE($O23,S$25,S$24),$A$2:$A$2943,$C$2:$C$2943)
A24: 39325 | B24: 11922.48 | C24: =(B24/B22-1)/(A24-A22)*360 | D24: =B24/$B$3*100 | P24: 31 | Q24: 28 | R24: 31 | S24: 30 | T24: 31 | U24: 30 | V24: 31 | W24: 31 | X24: 30 | Y24: 31 | Z24: 30 | AA24: 31 | AD24: (*) Acum a Mar
A25: 39353 | B25: 11975.61 | C25: =(B25/B24-1)/(A25-A24)*360 | D25: =B25/$B$3*100 | P25: 1 | Q25: 2 | R25: 3 | S25: 4 | T25: 5 | U25: 6 | V25: 7 | W25: 8 | X25: 9 | Y25: 10 | Z25: 11 | AA25: 12
A26: 39386 | B26: 12038.9 | C26: =(B26/B25-1)/(A26-A25)*360 | D26: =B26/$B$3*100 | O26: FONDO LIQUIDEZ RESERVA DÓLAR | P26: Ene | Q26: Feb | R26: Mar | S26: Abr | T26: May | U26: Jun | V26: Jul | W26: Ago | X26: Sep | Y26: Oct | Z26: Nov | AA26: Dic
A27: 39416 | B27: 12096.85 | C27: =(B27/B26-1)/(A27-A26)*360 | D27: =B27/$B$3*100 | O27: 2017 | T27: =LOOKUP(DATE($O27,T$25,T$24),$A$2:$A$2943,$I$2:$I$2943) | U27: =LOOKUP(DATE($O27,U$25,U$24),$A$2:$A$2943,$I$2:$I$2943) | V27: =LOOKUP(DATE($O27,V$25,V$24),$A$2:$A$2943,$I$2:$I$2943) | W27: =LOOKUP(DATE($O27,W$25,W$24),$A$2:$A$2943,$I$2:$I$2943) | X27: =LOOKUP(DATE($O27,X$25,X$24),$A$2:$A$2943,$I$2:$I$2943) | Y27: =LOOKUP(DATE($O27,Y$25,Y$24),$A$2:$A$2943,$I$2:$I$2943) | Z27: =LOOKUP(DATE($O27,Z$25,Z$24),$A$2:$A$2943,$I$2:$I$2943) | AA27: =LOOKUP(DATE($O27,AA$25,AA$24),$A$2:$A$2943,$I$2:$I$2943) | AD27: LIQUIDEZ RESERVA DÓLAR | AE27: Ene | AF27: Feb | AG27: Mar | AH27: Abr | AI27: May | AJ27: Jun | AK27: Jul | AL27: Ago | AM27: Sep | AN27: Oct | AO27: Nov | AP27: Dic | AQ27: Total Año | AW27: Rentabilidad | AX27: Mensual | AY27: Trimestral | AZ27: Semestral | BA27: Anual | BB27: Acum. 2026
A28: 39447 | B28: 12152.6 | C28: =(B28/B27-1)/(A28-A27)*360 | D28: =B28/$B$3*100 | O28: 2018 | P28: =LOOKUP(DATE($O28,P$25,P$24),$A$2:$A$2943,$I$2:$I$2943) | Q28: =LOOKUP(DATE($O28,Q$25,Q$24),$A$2:$A$2943,$I$2:$I$2943) | R28: =LOOKUP(DATE($O28,R$25,R$24),$A$2:$A$2943,$I$2:$I$2943) | S28: =LOOKUP(DATE($O28,S$25,S$24),$A$2:$A$2943,$I$2:$I$2943) | T28: =LOOKUP(DATE($O28,T$25,T$24),$A$2:$A$2943,$I$2:$I$2943) | U28: =LOOKUP(DATE($O28,U$25,U$24),$A$2:$A$2943,$I$2:$I$2943) | V28: =LOOKUP(DATE($O28,V$25,V$24),$A$2:$A$2943,$I$2:$I$2943) | W28: =LOOKUP(DATE($O28,W$25,W$24),$A$2:$A$2943,$I$2:$I$2943) | ... AA28: =LOOKUP(DATE($O28,AA$25,AA$24),$A$2:$A$2943,$I$2:$I$2943) | AD28: 2017 | AR28: (*) | AW28: Competencia | AX28: =($AW20/AX20-1)/(AW19-AX19)*360 | AY28: =($AW20/AY20-1)/($AW$19-AY19)*360 | AZ28: =($AW20/AZ20-1)/($AW$19-AZ19)*360 | BA28: =($AW20/BA20-1)/($AW$19-BA19)*360 | BB28: =AQ80
A29: 39478 | B29: 12223.14 | C29: =(B29/B28-1)/(A29-A28)*360 | D29: =B29/$B$3*100 | O29: 2019 | P29: =LOOKUP(DATE($O29,P$25,P$24),$A$2:$A$2943,$I$2:$I$2943) | Q29: =LOOKUP(DATE($O29,Q$25,Q$24),$A$2:$A$2943,$I$2:$I$2943) | R29: =LOOKUP(DATE($O29,R$25,R$24),$A$2:$A$2943,$I$2:$I$2943) | S29: =LOOKUP(DATE($O29,S$25,S$24),$A$2:$A$2943,$I$2:$I$2943) | T29: =LOOKUP(DATE($O29,T$25,T$24),$A$2:$A$2943,$I$2:$I$2943) | U29: =LOOKUP(DATE($O29,U$25,U$24),$A$2:$A$2943,$I$2:$I$2943) | V29: =LOOKUP(DATE($O29,V$25,V$24),$A$2:$A$2943,$I$2:$I$2943) | W29: =LOOKUP(DATE($O29,W$25,W$24),$A$2:$A$2943,$I$2:$I$2943) | ... AA29: =LOOKUP(DATE($O29,AA$25,AA$24),$A$2:$A$2943,$I$2:$I$2943) | AD29: 2018 | AW29: LIQUIDEZ RESERVA DÓLAR | AX29: =($AW21/AX21-1)/($AW$19-AX19)*360 | AY29: =($AW21/AY21-1)/($AW$19-AY19)*360 | AZ29: =($AW21/AZ21-1)/($AW$19-AZ19)*360 | BA29: =($AW21/BA21-1)/($AW$19-BA19)*360 | BB29: =+AQ81
A30: 39507 | B30: 12284.88 | C30: =(B30/B29-1)/(A30-A29)*360 | D30: =B30/$B$3*100 | O30: 2020 | P30: =LOOKUP(DATE($O30,P$25,P$24),$A$2:$A$2943,$I$2:$I$2943) | Q30: =LOOKUP(DATE($O30,Q$25,Q$24)+1,$A$2:$A$2943,$I$2:$I$2943) | R30: =LOOKUP(DATE($O30,R$25,R$24),$A:$A,$I:$I) | S30: =LOOKUP(DATE($O30,S$25,S$24),$A:$A,$I:$I) | T30: =LOOKUP(DATE($O30,T$25,T$24),$A:$A,$I:$I) | U30: =LOOKUP(DATE($O30,U$25,U$24),$A:$A,$I:$I) | V30: =LOOKUP(DATE($O30,V$25,V$24),$A:$A,$I:$I) | W30: =LOOKUP(DATE($O30,W$25,W$24),$A:$A,$I:$I) | X30: =LOOKUP(DATE($O30,X$25,X$24),$A:$A,$I:$I) | Y30: =+I183 | Z30: =+I184 | AA30: =+I185 | AD30: 2019
A31: 39538 | B31: 12351.45 | C31: =(B31/B30-1)/(A31-A30)*360 | D31: =B31/$B$3*100 | O31: 2021 | P31: =+I186 | Q31: =+I187 | R31: =+I188 | S31: =+I189 | T31: =+I190 | U31: =+I191 | V31: =+I192 | W31: =+I193 | X31: =+I194 | Y31: =+I195 | Z31: =+I196 | AA31: =+I197 | AD31: 2020
A32: 39568 | B32: 12416.18 | C32: =(B32/B31-1)/(A32-A31)*360 | D32: =B32/$B$3*100 | O32: 2022 | P32: =+I198 | Q32: =+I199 | R32: =+I200 | S32: =+I201 | T32: =+I202 | U32: =+I203 | V32: =+I204 | W32: =+I205 | X32: =+I206 | Y32: =+I207 | Z32: =+I208 | AA32: =+I209 | AD32: 2021 | AJ32: =+U31 | AK32: =+V31 | AL32: =+W31 | AM32: =+X31 | AN32: =+Y31 | AO32: =+Z31 | AP32: =+AA31 | AQ32: =+(H197/H190-1)/COUNTA(AE32:AP32)*12
A33: 39598 | B33: 12481.48 | C33: =(B33/B32-1)/(A33-A32)*360 | D33: =B33/$B$3*100 | O33: 2023 | P33: =+I210 | Q33: =+I211 | R33: =+I212 | S33: =+I213 | T33: =+I214 | U33: =+I215 | V33: =+I216 | W33: =+I217 | X33: =+I218 | Y33: =+I219 | Z33: =+I220 | AA33: =+I221 | AD33: 2022 | AE33: =+P32 | AF33: =+Q32 | AG33: =+R32 | AH33: =+S32 | AI33: =+T32 | AJ33: =+U32 | AK33: =+V32 | AL33: =+W32 | ... AP33: =+AA32 | AQ33: =+(H209/H197-1)/COUNTA(AE33:AP33)*12
A34: 39629 | B34: 12552.23 | C34: =(B34/B33-1)/(A34-A33)*360 | D34: =B34/$B$3*100 | O34: 2024 | P34: =+I222 | Q34: =+I223 | R34: =+I224 | S34: =+I225 | T34: =+I226 | U34: =+I227 | V34: =+I228 | W34: =+I229 | X34: =+I230 | Y34: =+I231 | Z34: =+I232 | AA34: =+I233 | AD34: 2023 | AE34: =+P33 | AF34: =+Q33 | AG34: =+R33 | AH34: =+S33 | AI34: =+T33 | AJ34: =+U33 | AK34: =+V33 | AL34: =+W33 | ... AP34: =+AA33 | AQ34: =+(H221/H209-1)/COUNTA(AE34:AP34)*12
A35: 39660 | B35: 12628.9 | C35: =(B35/B34-1)/(A35-A34)*360 | D35: =B35/$B$3*100 | O35: 2025 | P35: =+I234 | Q35: 0 | R35: =+I236 | S35: =+I237 | T35: =+I238 | U35: =+I239 | V35: =+I240 | W35: =+I241 | X35: =+I242 | Y35: =+I243 | Z35: =+I244 | AA35: =+I245 | AD35: 2024 | AE35: =+P34 | AF35: =+Q34 | AG35: =+R34 | AH35: =+S34 | AI35: =+T34 | AJ35: =+U34 | AK35: =+V34 | AL35: =+W34 | ... AP35: =+AA34 | AQ35: =+(H233/H221-1)/COUNTA(AE35:AP35)*12
O36: 2026 | P36: =+I246 | Q36: =+I247 | R36: =+I248 | S36: =+I249 | T36: =+I250 | U36: =+I251 | AD36: 2025 | AE36: =+P35 | AF36: =+Q35 | AG36: =+R35 | AH36: =+S35 | AI36: =+T35 | AJ36: =+U35 | AK36: =+V35 | AL36: =+W35 | ... AP36: =+AA35 | AQ36: =+(H245/H234-1)/COUNTA(AE36:AP36)*12
A37: 39689 | B37: 12704.63 | C37: =(B37/B35-1)/(A37-A35)*360 | D37: =B37/$B$3*100 | P37: 31 | Q37: 28 | R37: 31 | S37: 30 | T37: 31 | U37: 30 | V37: 31 | W37: 31 | X37: 30 | Y37: 31 | Z37: 30 | AA37: 31 | AD37: 2026 | AE37: =+P36 | AF37: =+Q36 | AG37: =+R36 | AH37: =+S36 | AI37: =+T36/S36-1 | AJ37: =+U36/T36-1 | AQ37: =+(H249/H246-1)/COUNTA(AE37:AJ37)*12
A38: 39721 | B38: 12796.95 | C38: =(B38/B37-1)/(A38-A37)*360 | D38: =B38/$B$3*100 | P38: 1 | Q38: 2 | R38: 3 | S38: 4 | T38: 4 | U38: 6 | V38: 7 | W38: 8 | X38: 9 | Y38: 10 | Z38: 11 | AA38: 12 | AD38: (*) Acum a Mar | AR38: (*)
A39: 39752 | B39: 12885.37 | C39: =(B39/B38-1)/(A39-A38)*360 | D39: =B39/$B$3*100 | O39: Competencia | P39: Ene | Q39: Feb | R39: Mar | S39: Abr | T39: May | U39: Jun | V39: Jul | W39: Ago | X39: Sep | Y39: Oct | Z39: Nov | AA39: Dic | AD39: Competencia | AE39: Ene | AF39: Feb | AG39: Mar | AH39: Abr | AI39: May | AJ39: Jun | AK39: Jul | AL39: Ago | AM39: Sep | AN39: Oct | AO39: Nov | AP39: Dic | AQ39: Total Año
A40: 39780 | B40: 12970.93 | C40: =(B40/B39-1)/(A40-A39)*360 | D40: =B40/$B$3*100 | O40: 2017 | T40: =LOOKUP(DATE($O40,T$25,T$24),$A$2:$A$2943,$L$2:$L$2943) | U40: =LOOKUP(DATE($O40,U$25,U$24),$A$2:$A$2943,$L$2:$L$2943) | V40: =LOOKUP(DATE($O40,V$25,V$24),$A$2:$A$2943,$L$2:$L$2943) | W40: =LOOKUP(DATE($O40,W$25,W$24),$A$2:$A$2943,$L$2:$L$2943) | X40: =LOOKUP(DATE($O40,X$25,X$24),$A$2:$A$2943,$L$2:$L$2943) | Y40: =LOOKUP(DATE($O40,Y$25,Y$24),$A$2:$A$2943,$L$2:$L$2943) | Z40: =LOOKUP(DATE($O40,Z$25,Z$24),$A$2:$A$2943,$L$2:$L$2943) | AA40: =LOOKUP(DATE($O40,AA$25,AA$24),$A$2:$A$2943,$L$2:$L$2943) | AD40: 2017 | AI40: =+T40 | AJ40: =+U40 | AK40: =+V40 | AL40: =+W40 | AM40: =+X40 | AN40: =+Y40 | AO40: =+Z40 | AP40: =+AA40 | AQ40: =+(K149/K141-1)/8*12
A41: 39813 | B41: 13066.33 | C41: =(B41/B40-1)/(A41-A40)*360 | D41: =B41/$B$3*100 | O41: 2018 | P41: =LOOKUP(DATE($O41,P$25,P$24),$A$2:$A$2943,$L$2:$L$2943) | Q41: =LOOKUP(DATE($O41,Q$25,Q$24),$A$2:$A$2943,$L$2:$L$2943) | R41: =LOOKUP(DATE($O41,R$25,R$24),$A$2:$A$2943,$L$2:$L$2943) | S41: =LOOKUP(DATE($O41,S$25,S$24),$A$2:$A$2943,$L$2:$L$2943) | T41: =LOOKUP(DATE($O41,T$25,T$24),$A$2:$A$2943,$L$2:$L$2943) | U41: =LOOKUP(DATE($O41,U$25,U$24),$A$2:$A$2943,$L$2:$L$2943) | V41: =LOOKUP(DATE($O41,V$25,V$24),$A$2:$A$2943,$L$2:$L$2943) | W41: =LOOKUP(DATE($O41,W$25,W$24),$A$2:$A$2943,$L$2:$L$2943) | ... AA41: =LOOKUP(DATE($O41,AA$25,AA$24),$A$2:$A$2943,$L$2:$L$2943) | AD41: 2018 | AE41: =+P41 | AF41: =+Q41 | AG41: =+R41 | AH41: =+S41 | AI41: =+T41 | AJ41: =+U41 | AK41: =+V41 | AL41: =+W41 | ... AP41: =+AA41 | AQ41: =+K161/K149-1
A42: 39843 | B42: 13151.16 | C42: =(B42/B41-1)/(A42-A41)*360 | D42: =B42/$B$3*100 | O42: 2019 | P42: =LOOKUP(DATE($O42,P$25,P$24),$A$2:$A$2943,$L$2:$L$2943) | Q42: =LOOKUP(DATE($O42,Q$25,Q$24),$A$2:$A$2943,$L$2:$L$2943) | R42: =LOOKUP(DATE($O42,R$25,R$24),$A$2:$A$2943,$L$2:$L$2943) | S42: =LOOKUP(DATE($O42,S$25,S$24),$A$2:$A$2943,$L$2:$L$2943) | T42: =LOOKUP(DATE($O42,T$25,T$24),$A$2:$A$2943,$L$2:$L$2943) | U42: =LOOKUP(DATE($O42,U$25,U$24),$A$2:$A$2943,$L$2:$L$2943) | V42: =LOOKUP(DATE($O42,V$25,V$24),$A$2:$A$2943,$L$2:$L$2943) | W42: =LOOKUP(DATE($O42,W$25,W$24),$A$2:$A$2943,$L$2:$L$2943) | ... AA42: =LOOKUP(DATE($O42,AA$25,AA$24),$A$2:$A$2943,$L$2:$L$2943) | AD42: 2019 | AE42: =+P42 | AF42: =+Q42 | AG42: =+R42 | AH42: =+S42 | AI42: =+T42 | AJ42: =+U42 | AK42: =+V42 | AL42: =+W42 | ... AP42: =+AA42 | AQ42: =+(K173/K161-1)/COUNTA(AE42:AP42)*12
A43: 39871 | B43: 13212.09 | C43: =(B43/B42-1)/(A43-A42)*360 | D43: =B43/$B$3*100 | O43: 2020 | P43: =LOOKUP(DATE($O43,P$25,P$24),$A$2:$A$2943,$L$2:$L$2943) | Q43: =LOOKUP(DATE($O43,Q$25,Q$24)+1,$A$2:$A$2943,$L$2:$L$2943) | R43: =LOOKUP(DATE($O43,R$25,R$24),$A:$A,$L:$L) | S43: =LOOKUP(DATE($O43,S$25,S$24),$A:$A,$L:$L) | T43: =LOOKUP(DATE($O43,T$25,T$24),$A:$A,$L:$L) | U43: =LOOKUP(DATE($O43,U$25,U$24),$A:$A,$L:$L) | V43: =LOOKUP(DATE($O43,V$25,V$24),$A:$A,$L:$L) | W43: =LOOKUP(DATE($O43,W$25,W$24),$A:$A,$L:$L) | X43: =LOOKUP(DATE($O43,X$25,X$24),$A:$A,$L:$L) | Y43: =LOOKUP(DATE($O43,Y$25,Y$24),$A:$A,$L:$L) | ... AA43: =LOOKUP(DATE($O43,AA$25,AA$24),$A:$A,$L:$L) | AD43: 2020 | AE43: =+P43 | AF43: =+Q43 | AG43: =+R43 | AH43: =+S43 | AI43: =+T43 | AJ43: =+U43 | AK43: =+V43 | AL43: =+W43 | ... AP43: =+AA43 | AQ43: =+(K185/K173-1)/COUNTA(AE43:AP43)*12
A44: 39903 | B44: 13251.18 | C44: =(B44/B43-1)/(A44-A43)*360 | D44: =B44/$B$3*100 | O44: 2021 | P44: =+L186 | Q44: =+L187 | R44: =+L188 | S44: =+L189 | T44: =+L190 | U44: =+L191 | V44: =+L192 | W44: =+L193 | X44: =+L194 | Y44: =+L195 | Z44: =+L196 | AA44: =+L197 | AD44: 2021 | AE44: =+P44 | AF44: =+Q44 | AG44: =+R44 | AH44: =+S44 | AI44: =+T44 | AJ44: =+U44 | AK44: =+V44 | AL44: =+W44 | ... AP44: =+AA44 | AQ44: =+(K196/K185-1)/COUNTA(AE44:AP44)*12
A45: 39933 | B45: 13272.62 | C45: =(B45/B44-1)/(A45-A44)*360 | D45: =B45/$B$3*100 | O45: 2022 | P45: =+L198 | Q45: =+L199 | R45: =+L200 | S45: =+L201 | T45: =+L202 | U45: =+L203 | V45: =+L204 | W45: =+L205 | X45: =+L206 | Y45: =+L207 | Z45: =+L208 | AA45: =+L209 | AD45: 2022 | AE45: =+P45 | AF45: =+Q45 | AG45: =+R45 | AH45: =+S45 | AI45: =+T45 | AJ45: =+U45 | AK45: =+V45 | AL45: =+W45 | ... AP45: =+AA45 | AQ45: =+(K209/K197-1)/COUNTA(AE45:AP45)*12
A46: 39962 | B46: 13286.96 | C46: =(B46/B45-1)/(A46-A45)*360 | D46: =B46/$B$3*100 | O46: 2023 | P46: =+L210 | Q46: =+L211 | R46: =+L212 | S46: =+L213 | T46: =+L214 | U46: =+L215 | V46: =+L216 | W46: =+L217 | X46: =+L218 | Y46: =+L219 | Z46: =+L220 | AA46: =+L221 | AD46: 2023 | AE46: =+P46 | AF46: =+Q46 | AG46: =+R46 | AH46: =+S46 | AI46: =+T46 | AJ46: =+U46 | AK46: =+V46 | AL46: =+W46 | ... AP46: =+AA46 | AQ46: =+(K221/K209-1)/COUNTA(AE46:AP46)*12
A47: 39994 | B47: 13299.08 | C47: =(B47/B46-1)/(A47-A46)*360 | D47: =B47/$B$3*100 | O47: 2024 | P47: =+L222 | Q47: =+L223 | R47: =+L224 | S47: =+L225 | T47: =+L226 | U47: =+L227 | V47: =+L228 | W47: =+L229 | X47: =+L230 | Y47: =+L231 | Z47: =+L232 | AA47: =+L233 | AD47: 2024 | AE47: =+P47 | AF47: =+Q47 | AG47: =+R47 | AH47: =+S47 | AI47: =+T47 | AJ47: =+U47 | AK47: =+V47 | AL47: =+W47 | ... AP47: =+AA47 | AQ47: =+(K232/K221-1)/COUNTA(AE47:AP47)*12
A48: 40025 | B48: 13305.34 | C48: =(B48/B47-1)/(A48-A47)*360 | D48: =B48/$B$3*100 | O48: 2025 | P48: 0 | Q48: 0 | R48: =+L236 | S48: =+L237 | T48: =+L238 | U48: =+L239 | V48: =+L240 | W48: =+L241 | X48: =+L242 | Y48: =+L243 | Z48: =+L244 | AA48: =+L245 | AD48: 2025 | AE48: =+P48 | AF48: =+Q48 | AG48: =+R48 | AH48: =+S48 | AI48: =+T48 | AJ48: =+U48 | AK48: =+V48 | AL48: =+W48 | ... AP48: =+AA48 | AQ48: =+(K245/K234-1)/COUNTA(AE48:AP48)*12
A49: 40056 | B49: 13310.07 | C49: =(B49/B48-1)/(A49-A48)*360 | D49: =B49/$B$3*100 | O49: 2026 | P49: =+L246 | Q49: =+L247 | R49: =+L248 | S49: =+L249 | T49: =+L250 | U49: =+L251 | AD49: 2026 | AE49: =+P49 | AF49: =+Q49 | AG49: =+R49 | AH49: =+S49 | AI49: =+T49/S49-1 | AJ49: =+U49/T49-1 | AQ49: =+(K249/K246-1)/COUNTA(AE49:AJ49)*12
A50: 40086 | B50: 13315.05 | C50: =(B50/B49-1)/(A50-A49)*360 | D50: =B50/$B$3*100
A51: 40116 | B51: 13319.74 | C51: =(B51/B50-1)/(A51-A50)*360 | D51: =B51/$B$3*100 | AD51: (*) Acum a Mar
A52: 40147 | B52: 13324.51 | C52: =(B52/B51-1)/(A52-A51)*360 | D52: =B52/$B$3*100
A53: 40178 | B53: 13329.5 | C53: =(B53/B52-1)/(A53-A52)*360 | D53: =B53/$B$3*100 | AC53: Año | AD53: Fondo | AE53: Ene | AF53: Feb | AG53: Mar | AH53: Abr | AI53: May | AJ53: Jun | AK53: Jul | AL53: Ago | AM53: Sep | AN53: Oct | AO53: Nov | AP53: Dic | AQ53: Total Año
A54: 40207 | B54: 13334.25 | C54: =(B54/B53-1)/(A54-A53)*360 | D54: =B54/$B$3*100 | AC54: =+AD12 | AD54: ICP
A55: 40235 | B55: 13338.53 | C55: =(B55/B54-1)/(A55-A54)*360 | D55: =B55/$B$3*100 | AC55: =+AD13 | AD55: ICP
A56: 40268 | B56: 13343.79 | C56: =(B56/B55-1)/(A56-A55)*360 | D56: =B56/$B$3*100 | AC56: =+AD14 | AD56: ICP
A57: 40298 | B57: 13348.63 | C57: =(B57/B56-1)/(A57-A56)*360 | D57: =B57/$B$3*100 | AC57: =+AD15 | AD57: ICP
A58: 40329 | B58: 13353.5 | C58: =(B58/B57-1)/(A58-A57)*360 | D58: =B58/$B$3*100 | AC58: 2020 | AD58: ICP
A59: 40359 | B59: 13360.9 | C59: =(B59/B58-1)/(A59-A58)*360 | D59: =B59/$B$3*100 | AC59: 2017 | AD59: Competencia
A60: 40389 | B60: 13373.99 | C60: =(B60/B59-1)/(A60-A59)*360 | D60: =B60/$B$3*100 | AD60: LIQUIDEZ RESERVA DÓLAR
A61: 40421 | B61: 13395.21 | C61: =(B61/B60-1)/(A61-A60)*360 | D61: =B61/$B$3*100 | AC61: 2018 | AD61: Competencia
A62: 40451 | B62: 13419.79 | C62: =(B62/B61-1)/(A62-A61)*360 | D62: =B62/$B$3*100 | AD62: LIQUIDEZ RESERVA DÓLAR
A63: 40480 | B63: 13448.69 | C63: =(B63/B62-1)/(A63-A62)*360 | D63: =B63/$B$3*100 | AC63: 2019 | AD63: Competencia
A64: 40512 | B64: 13483.02 | C64: =(B64/B63-1)/(A64-A63)*360 | D64: =B64/$B$3*100 | AD64: LIQUIDEZ RESERVA DÓLAR
A65: 40543 | B65: 13522.93 | C65: =(B65/B64-1)/(A65-A64)*360 | D65: =B65/$B$3*100 | AC65: 2020 | AD65: Competencia
A66: 40574 | B66: 13557.12 | C66: =(B66/B65-1)/(A66-A65)*360 | D66: =B66/$B$3*100 | AD66: LIQUIDEZ RESERVA DÓLAR
A67: 40602 | B67: 13592.3 | C67: =(B67/B66-1)/(A67-A66)*360 | D67: =B67/$B$3*100 | AD67: ICP | AJ67: =+AJ17 | AK67: =+AK17 | AL67: =+AL17 | AM67: =+AM17 | AN67: =+AN17 | AO67: =+AO17 | AP67: =+AP17 | AQ67: =+AQ17
A68: 40633 | B68: 13635.91 | C68: =(B68/B67-1)/(A68-A67)*360 | D68: =B68/$B$3*100 | AC68: 2021 | AD68: Competencia | AJ68: =+AJ44 | AK68: =+AK44 | AL68: =+AL44 | AM68: =+AM44 | AN68: =+AN44 | AO68: =+AO44 | AP68: =+AP44 | AQ68: =+AQ44
A69: 40662 | B69: 13682.94 | C69: =(B69/B68-1)/(A69-A68)*360 | D69: =B69/$B$3*100 | AD69: LIQUIDEZ RESERVA DÓLAR | AJ69: =+AJ32 | AK69: =+AK32 | AL69: =+AL32 | AM69: =+AM32 | AN69: =+AN32 | AO69: =+AO32 | AP69: =+AP32 | AQ69: =+AQ32
A70: 40694 | B70: 13741.06 | C70: =(B70/B69-1)/(A70-A69)*360 | D70: =B70/$B$3*100 | AD70: ICP | AE70: =+AE18 | AF70: =+AF18 | AG70: =+AG18 | AH70: =+AH18 | AI70: =+AI18 | AJ70: =+AJ18 | AK70: =+AK18 | AL70: =+AL18 | ... AQ70: =+AQ18
A71: 40724 | B71: 13799.74 | C71: =(B71/B70-1)/(A71-A70)*360 | D71: =B71/$B$3*100 | AC71: 2022 | AD71: Competencia | AE71: =+AE45 | AF71: =+AF45 | AG71: =+AG45 | AH71: =+AH45 | AI71: =+AI45 | AJ71: =+AJ45 | AK71: =+AK45 | AL71: =+AL45 | ... AQ71: =+AQ45 | AR71: (*)
A72: 40753 | B72: 13858.14 | C72: =(B72/B71-1)/(A72-A71)*360 | D72: =B72/$B$3*100 | AD72: LIQUIDEZ RESERVA DÓLAR | AE72: =+AE33 | AF72: =+AF33 | AG72: =+AG33 | AH72: =+AH33 | AI72: =+AI33 | AJ72: =+AJ33 | AK72: =+AK33 | AL72: =+AL33 | ... AQ72: =+AQ33
A73: 40786 | B73: 13925.03 | C73: =(B73/B72-1)/(A73-A72)*360 | D73: =B73/$B$3*100 | AD73: ICP | AE73: =+AE24 | AF73: =+AF24 | AG73: =+AG24 | AH73: =+AH24 | AI73: =+AI24 | AJ73: =+AJ24 | AK73: =+AK24 | AL73: =+AL24 | ... AQ73: =+AQ24
A74: 40816 | B74: 13985.97 | C74: =(B74/B73-1)/(A74-A73)*360 | D74: =B74/$B$3*100 | AC74: 2023 | AD74: Competencia | AE74: =+AE46 | AF74: =+AF46 | AG74: =+AG46 | AH74: =+AH46 | AI74: =+AI46 | AJ74: =+AJ46 | AK74: =+AK46 | AL74: =+AL46 | ... AQ74: =+AQ46
A75: 40847 | B75: 14043.21 | C75: =(B75/B74-1)/(A75-A74)*360 | D75: =B75/$B$3*100 | AD75: LIQUIDEZ RESERVA DÓLAR | AE75: =+AE34 | AF75: =+AF34 | AG75: =+AG34 | AH75: =+AH34 | AI75: =+AI34 | AJ75: =+AJ34 | AK75: =+AK34 | AL75: =+AL34 | ... AQ75: =+AQ34
A76: 40877 | B76: 14110.87 | C76: =(B76/B75-1)/(A76-A75)*360 | D76: =B76/$B$3*100 | AC76: 2024 | AD76: Competencia | AE76: =+AE47 | AF76: =+AF47 | AG76: =+AG47 | AH76: =+AH47 | AI76: =+AI47 | AJ76: =+AJ47 | AK76: =+AK47 | AL76: =+AL47 | ... AQ76: =+AQ47
A77: 40907 | B77: 14172.63 | C77: =(B77/B76-1)/(A77-A76)*360 | D77: =B77/$B$3*100 | AD77: LIQUIDEZ RESERVA DÓLAR | AE77: =+AE35 | AF77: =+AF35 | AG77: =+AG35 | AH77: =+AH35 | AI77: =+AI35 | AJ77: =+AJ35 | AK77: =+AK35 | AL77: =+AL35 | ... AQ77: =+AQ35
A78: 40939 | B78: 14236.38 | C78: =(B78/B77-1)/(A78-A77)*360 | D78: =B78/$B$3*100 | AC78: 2025 | AD78: Competencia | AE78: =+AE48 | AF78: =+AF48 | AG78: =+AG48 | AH78: =+AH48 | AI78: =+AI48 | AJ78: =+AJ48 | AK78: =+AK48 | AL78: =+AL48 | ... AQ78: =+AQ48
A79: 40968 | B79: 14293.67 | C79: =(B79/B78-1)/(A79-A78)*360 | D79: =B79/$B$3*100 | AD79: LIQUIDEZ RESERVA DÓLAR | AE79: =+AE36 | AF79: =+AF36 | AG79: =+AG36 | AH79: =+AH36 | AI79: =+AI36 | AJ79: =+AJ36 | AK79: =+AK36 | AL79: =+AL36 | ... AQ79: =+AQ36
A80: 40998 | B80: 14353.34 | C80: =(B80/B79-1)/(A80-A79)*360 | D80: =B80/$B$3*100 | AC80: 2025 | AD80: Competencia | AE80: =+AE49 | AF80: =+AF49 | AG80: =+AG49 | AH80: =+AH49 | AQ80: =+AQ49
A81: 41029 | B81: 14415.21 | C81: =(B81/B80-1)/(A81-A80)*360 | D81: =B81/$B$3*100 | AD81: LIQUIDEZ RESERVA DÓLAR | AE81: =+AE37 | AF81: =+AF37 | AG81: =+AG37 | AH81: =+AH37 | AQ81: =+AQ37
A82: 41060 | B82: 14477.55 | C82: =(B82/B81-1)/(A82-A81)*360 | D82: =B82/$B$3*100
A83: 41089 | B83: 14536.13 | C83: =(B83/B82-1)/(A83-A82)*360 | D83: =B83/$B$3*100
A84: 41121 | B84: 14600.61 | C84: =(B84/B83-1)/(A84-A83)*360 | D84: =B84/$B$3*100
A85: 41152 | B85: 14663.33 | C85: =(B85/B84-1)/(A85-A84)*360 | D85: =B85/$B$3*100
A86: 41180 | B86: 14720.68 | C86: =(B86/B85-1)/(A86-A85)*360 | D86: =B86/$B$3*100
A87: 41213 | B87: 14788.56 | C87: =(B87/B86-1)/(A87-A86)*360 | D87: =B87/$B$3*100 | AC87: (*) Acum a Mar
A88: 41243 | B88: 14850.38 | C88: =(B88/B87-1)/(A88-A87)*360 | D88: =B88/$B$3*100
A89: 41274 | B89: 14908.2 | C89: =(B89/B88-1)/(A89-A88)*360 | D89: =B89/$B$3*100
A90: 41305 | B90: 14978.58 | C90: =(B90/B89-1)/(A90-A89)*360 | D90: =B90/$B$3*100
A91: 41333 | B91: 15036.94 | C91: =(B91/B90-1)/(A91-A90)*360 | D91: =B91/$B$3*100
A92: 41362 | B92: 15095.51 | C92: =(B92/B91-1)/(A92-A91)*360 | D92: =B92/$B$3*100
A93: 41394 | B93: 15164.77 | C93: =(B93/B92-1)/(A93-A92)*360 | D93: =B93/$B$3*100
A94: 41425 | B94: 15230.38 | C94: =(B94/B93-1)/(A94-A93)*360 | D94: =B94/$B$3*100 | AD94: 42886
A95: 41453 | B95: 15289.74 | C95: =(B95/B94-1)/(A95-A94)*360 | D95: =B95/$B$3*100 | AD95: 42916
A96: 41486 | B96: 15360.27 | C96: =(B96/B95-1)/(A96-A95)*360 | D96: =B96/$B$3*100 | AD96: 42947
A97: 41516 | B97: 15424.43 | C97: =(B97/B96-1)/(A97-A96)*360 | D97: =B97/$B$3*100 | AD97: 42978
A98: 41547 | B98: 15490.99 | C98: =(B98/B97-1)/(A98-A97)*360 | D98: =B98/$B$3*100 | AD98: 43008
A99: 41578 | B99: 15554.36 | C99: =(B99/B98-1)/(A99-A98)*360 | D99: =B99/$B$3*100 | AD99: 43039
A100: 41607 | B100: 15615.06 | C100: =(B100/B99-1)/(A100-A99)*360 | D100: =B100/$B$3*100 | AD100: 43069
...

Sheet rentabilidad
S1: Rentabilidad | T1: Mensual | U1: Trimestral | V1: Semestral | W1: Anual | X1: Acum 2026 (*)
S2: Competencia | T2: =+'Datos ICP (2)'!AX28 | U2: =+'Datos ICP (2)'!AY28 | V2: =+'Datos ICP (2)'!AZ28 | W2: =+'Datos ICP (2)'!BA28 | X2: =+'Datos ICP (2)'!BB28
S3: LIQUIDEZ RESERVA DÓLAR | T3: =+'Datos ICP (2)'!AX29 | U3: =+'Datos ICP (2)'!AY29 | V3: =+'Datos ICP (2)'!AZ29 | W3: =+'Datos ICP (2)'!BA29 | X3: =+'Datos ICP (2)'!BB29
C6: Año | D6: Fondo | E6: Ene | F6: Feb | G6: Mar | H6: Abr | I6: May | J6: Jun | K6: Jul | L6: Ago | M6: Sep | N6: Oct | O6: Nov | P6: Dic | Q6: Total Año
C8: 2017 | D8: Competencia
D9: LIQUIDEZ DÓLAR
C10: 2018 | D10: Competencia
D11: LIQUIDEZ DÓLAR
C12: 2019 | D12: Competencia
D13: LIQUIDEZ DÓLAR
C14: 2020 | D14: Competencia
D15: LIQUIDEZ DÓLAR
C16: 2021 | D16: Competencia
D17: LIQUIDEZ RESERVA DÓLAR
C18: 2022 | D18: Competencia
D19: LIQUIDEZ DÓLAR
C20: 2023 | D20: Competencia
D21: LIQUIDEZ RESERVA DÓLAR
C22: 2024 | D22: Competencia
D23: LIQUIDEZ RESERVA DÓLAR | Q23: 0
C24: 2025 | D24: Competencia | G24: =+'Datos ICP (2)'!AG78 | H24: =+'Datos ICP (2)'!AH78 | I24: =+'Datos ICP (2)'!AI78 | J24: =+'Datos ICP (2)'!AJ78 | K24: =+'Datos ICP (2)'!AK78 | L24: =+'Datos ICP (2)'!AL78 | M24: =+'Datos ICP (2)'!AM78 | N24: =+'Datos ICP (2)'!AN78 | ... Q24: =+'Datos ICP (2)'!AQ78
D25: LIQUIDEZ RESERVA DÓLAR | G25: =+'Datos ICP (2)'!AG79 | H25: =+'Datos ICP (2)'!AH79 | I25: =+'Datos ICP (2)'!AI79 | J25: =+'Datos ICP (2)'!AJ79 | K25: =+'Datos ICP (2)'!AK79 | L25: =+'Datos ICP (2)'!AL79 | M25: =+'Datos ICP (2)'!AM79 | N25: =+'Datos ICP (2)'!AN79 | ... Q25: =+'Datos ICP (2)'!AQ79
C26: 2026 | D26: Competencia | E26: =+'Datos ICP (2)'!AE80 | F26: =+'Datos ICP (2)'!AF80 | G26: =+'Datos ICP (2)'!AG80 | H26: =+'Datos ICP (2)'!AH80 | Q26: =+'Datos ICP (2)'!AQ80
D27: LIQUIDEZ RESERVA DÓLAR | E27: =+'Datos ICP (2)'!AE81 | F27: =+'Datos ICP (2)'!AF81 | G27: =+'Datos ICP (2)'!AG81 | H27: =+'Datos ICP (2)'!AH81 | Q27: =+'Datos ICP (2)'!AQ81

Sheet composición
J1: Duración | N1: Instrumentos | R1: Moneda
O2: Bono | P2: 0
K3: Menos de 1 mes | L3: 0.1757 | O3: Depósitos | P3: 0 | S3: USD | T3: 1
K4: 1-3 meses | L4: 0.6108 | O4: Factoring | P4: 0
K5: 3-4 meses | L5: 0.2135 | O5: Financiamiento Inmobiliario | P5: 0
K6: Más de 4 meses | L6: 0 | O6: Financiamiento Mesa Moneda Extranjera | P6: 0.8108
L7: =SUM(L3:L6) | O7: Garantías | P7: 0
O8: Nota Estructurada | P8: 0.1892
O9: Financiamiento Mesa Renta Fija | P9: 0
O10: Simultánea | P10: 0
O11: Efectos de Comercio | P11: 0
O13: Pagaré | P13: 0
A14: Facturas | B14: 0
P15: =SUM(P2:P13)
